[{"name": "人类的群星闪耀时", "url": "https://book.douban.com/subject/1083762/", "comment_num": 13405, "sub_tag_name": "茨威格", "tag_name": "文学", "score": 8.7, "book_id": "1083762", "description": "《人类群星闪耀时》由奥地利著名小说家创作。《人类群星闪耀时》内容：涌动着匪徒、探险家、叛乱者兼英雄血液的巴尔沃亚成为第一个看到太平洋的欧洲人；仅仅一秒钟的优..."},
{"name": "一个陌生女人的来信", "url": "https://book.douban.com/subject/2154960/", "comment_num": 47134, "sub_tag_name": "茨威格", "tag_name": "文学", "score": 8.7, "book_id": "2154960", "description": "这是一部短篇小说集，除《一个陌生女人的来信》，亦按时间顺序收录了《火烧火燎的秘密》、《马来狂人》等名篇，作者的创作历程一目了然。《一个陌生女人的来信》讲述..."},
{"name": "昨日的世界", "url": "https://book.douban.com/subject/1062343/", "comment_num": 6555, "sub_tag_name": "茨威格", "tag_name": "文学", "score": 9.2, "book_id": "1062343", "description": "作者以饱满真挚的感情、平实顺畅的文宇叙述了他所认识的特定时期的各种人物，他亲身经历的社会政治事件，他对那个动荡不安的时代的感受，记录了当时欧洲从一战前夜到二..."},
{"name": "象棋的故事", "url": "https://book.douban.com/subject/2158684/", "comment_num": 5513, "sub_tag_name": "茨威格", "tag_name": "文学", "score": 9.0, "book_id": "2158684", "description": "《象棋的故事》是茨威格生前发表的最后一部中篇小说。小说表面上讲述了一条从纽约开往南美的轮船上一位业余国际象棋手击败了国际象棋世界冠军的故事，实际上倾诉了纳粹..."},
{"name": "心灵的焦灼", "url": "https://book.douban.com/subject/2146279/", "comment_num": 2530, "sub_tag_name": "茨威格", "tag_name": "文学", "score": 8.9, "book_id": "2146279", "description": "同情恰好有两种。一种同情怯懦感伤，实际上只是心灵的焦灼。看到别人的不幸，急于尽快地脱身出来，以免受到感动，陷入难堪的境地。这种同情根本不是对别人的痛苦抱有同..."},
{"name": "一个陌生女子的来信", "url": "https://book.douban.com/subject/1159939/", "comment_num": 22823, "sub_tag_name": "茨威格", "tag_name": "文学", "score": 8.6, "book_id": "1159939", "description": "收作者《一个陌生女子的来信》、《家庭女教师》等5部小说。"},
{"name": "恐惧", "url": "https://book.douban.com/subject/10563555/", "comment_num": 1423, "sub_tag_name": "茨威格", "tag_name": "文学", "score": 8.9, "book_id": "10563555", "description": "名家名作名译——悦经典01探索女性终极心灵之谜讴歌人类情感至高奇迹★《一个陌生女人的来信》作者茨威格最值得珍藏的经典中篇全收录！★著名德语翻译家韩耀..."},
{"name": "斯·茨威格中短篇小说选", "url": "https://book.douban.com/subject/1818583/", "comment_num": 2324, "sub_tag_name": "茨威格", "tag_name": "文学", "score": 9.1, "book_id": "1818583", "description": "茨威格初登文坛时，是以抒情诗人的面貌出现的，接着又进行戏剧创作。奥地利作家，不少是诗人、小说家兼剧作家，施尼茨勒、霍夫曼斯塔尔和茨威格均是如此。早在大学时代..."},
{"name": "异端的权利", "url": "https://book.douban.com/subject/1465543/", "comment_num": 1616, "sub_tag_name": "茨威格", "tag_name": "文学", "score": 8.8, "book_id": "1465543", "description": "三联文化生活译丛7.75印张123千字"},
{"name": "一个政治性人物的肖像", "url": "https://book.douban.com/subject/2146277/", "comment_num": 844, "sub_tag_name": "茨威格", "tag_name": "文学", "score": 9.1, "book_id": "2146277", "description": "本书是茨威格继《三大师》等作家传记之后创作的历史人物传记的第一部。这些传记的特色便是心理分析。《一个政治性人物的肖像》在1929年面世，是他开始创作的一系..."},
{"name": "茨威格文集", "url": "https://book.douban.com/subject/26352569/", "comment_num": 327, "sub_tag_name": "茨威格", "tag_name": "文学", "score": 9.3, "book_id": "26352569", "description": "文集精选茨威格不同创作时期的重要作品，尤其侧重作者艺术成就最高、最受读者喜爱的中短篇小说。第一卷包括《夜色朦胧》《马来狂人》《一个陌生女人的来信》《看不见的..."},
{"name": "昨日之旅", "url": "https://book.douban.com/subject/4173402/", "comment_num": 2820, "sub_tag_name": "茨威格", "tag_name": "文学", "score": 8.4, "book_id": "4173402", "description": "《昨日之旅》是《一个陌生女人的来信》作者斯台芬·茨威格的遗作，由国内最权威的茨威格研究和翻译家张玉书先生鼎力翻译。这是一个感伤的爱情故事。男主人公路德维希..."},
{"name": "巴西：未来之国", "url": "https://book.douban.com/subject/21714777/", "comment_num": 493, "sub_tag_name": "茨威格", "tag_name": "文学", "score": 8.2, "book_id": "21714777", "description": "《巴西：未来之国》出版于1941年，今天读来，依然是一本了解巴西的最佳书籍。前三章历史、经济和文化，从总体上介绍巴西；后几章则是巴西主要城市的介绍，有游览..."},
{"name": "一个陌生女人的来信", "url": "https://book.douban.com/subject/1051745/", "comment_num": 1642, "sub_tag_name": "茨威格", "tag_name": "文学", "score": 8.7, "book_id": "1051745", "description": "本书收集了的小说抛充了许多外在的细节真实，把注意力集中到人物的内心世界，人物的性格，隐蔽的内在激情。读者注意到作者把一切在他看来可有可无之物悉数删去，无论马..."},
{"name": "变形的陶醉", "url": "https://book.douban.com/subject/6730333/", "comment_num": 780, "sub_tag_name": "茨威格", "tag_name": "文学", "score": 8.6, "book_id": "6730333", "description": "出身寒微的邮务员克丽丝蒂娜因一次偶然的机会跻身上层社会，让众多纨绔子弟为之倾倒，她本人也沉醉于这飘忽的美梦之中，但好景不长，仅仅过了十天她的富贵梦便破灭了。..."},
{"name": "茨威格小说集", "url": "https://book.douban.com/subject/1760134/", "comment_num": 608, "sub_tag_name": "茨威格", "tag_name": "文学", "score": 9.1, "book_id": "1760134", "description": "中短篇小说十六篇灼人的秘密夏天的故事桎梏恐惧热带癫狂症患者奇妙之夜巫山云（一个陌生女人的来信）月光巷看不见的收藏..."},
{"name": "玛丽·斯图亚特", "url": "https://book.douban.com/subject/1065485/", "comment_num": 501, "sub_tag_name": "茨威格", "tag_name": "文学", "score": 8.6, "book_id": "1065485", "description": "任何一件文献，尽管它的悠久历史经过周密的考证，尽管它是货真价实的归档材料，却保证不了它的可靠性和叙事人的公允。同一件事，在同时几位史家的记载中，却有南辕北辙..."},
{"name": "情感的迷惘", "url": "https://book.douban.com/subject/1316564/", "comment_num": 617, "sub_tag_name": "茨威格", "tag_name": "文学", "score": 9.0, "book_id": "1316564", "description": "本书为“译林世界文学名著.现当代系列”丛书之一。斯.茨威格是享有世界声誉的奥地利作家。他的小说善于通过心理描写，揭示人物的内心世界，具有强烈的艺术魅力和社会..."},
{"name": "一个陌生女人的来信", "url": "https://book.douban.com/subject/1083483/", "comment_num": 2041, "sub_tag_name": "茨威格", "tag_name": "文学", "score": 8.6, "book_id": "1083483", "description": "一个五月的下午，读一个陌生女人的来信，信中的语言是一把锋锐而温情的刀，将心尖薄薄的划开。一个陌生女人，一个曾经的邻家少女，一个看不见的女人，她时而飘浮不定，..."},
{"name": "蒙田", "url": "https://book.douban.com/subject/3320904/", "comment_num": 498, "sub_tag_name": "茨威格", "tag_name": "文学", "score": 8.5, "book_id": "3320904", "description": "茨威格的最后一部传记作品，刻画了蒙田这位“达观宁静和退隐到自我中的高手和导师”，一个在任何情况下都“竭力争取内心自由的先驱战士”的形象。茨威格在写本书时所面..."},
{"name": "陌生女人的来信", "url": "https://book.douban.com/subject/26745030/", "comment_num": 951, "sub_tag_name": "茨威格", "tag_name": "文学", "score": 8.7, "book_id": "26745030", "description": "【内容简介】《陌生女人的来信》是茨威格最著名的代表作，曾被徐静蕾拍过电影，被孟京辉改编为话剧，反响热烈。作家R在41岁生日那天收到一封没有署名和地址的信，..."},
{"name": "一个陌生女人的来信", "url": "https://book.douban.com/subject/1123546/", "comment_num": 967, "sub_tag_name": "茨威格", "tag_name": "文学", "score": 8.8, "book_id": "1123546", "description": "《一个陌生女人的来信》收集了奥地利作家茨威格十二篇小说，小说抛弃了许多外在的细节，把注意力集中到人物的内心世界，人物的性格，隐蔽的内在激情的描写。读者注..."},
{"name": "断头王后", "url": "https://book.douban.com/subject/1051524/", "comment_num": 1032, "sub_tag_name": "茨威格", "tag_name": "文学", "score": 8.4, "book_id": "1051524", "description": "本书是茨威格的人物传记作品中，最为人称道的作品之一，出版后曾轰动欧洲。玛丽·安托瓦内特天生丽质，却成了母亲政治棋盘上的一颗棋子，15岁远嫁法国，与当时还是..."},
{"name": "茨威格小说精选", "url": "https://book.douban.com/subject/1068641/", "comment_num": 1032, "sub_tag_name": "茨威格", "tag_name": "文学", "score": 8.9, "book_id": "1068641", "description": "茨威格一生共写了十二部传记，九部散文集，七部戏剧，两部长篇，三部诗集，六部小说集，以及一部自传等。它们确保了他在德语文学乃至世界文学中的地位。他成为一位深受..."},
{"name": "三大师", "url": "https://book.douban.com/subject/1438426/", "comment_num": 215, "sub_tag_name": "茨威格", "tag_name": "文学", "score": 8.4, "book_id": "1438426", "description": "斯特凡·茨威格在二十年代相继完成了以《世界建筑师》为总标题的三部传记：《三大师》、《三诗人的生平》和《与魔的博斗》。其中描写三位十九世纪“独特的伟大小说家”..."},
{"name": "一个女人一生中的二十四小时", "url": "https://book.douban.com/subject/26374535/", "comment_num": 143, "sub_tag_name": "茨威格", "tag_name": "文学", "score": 9.0, "book_id": "26374535", "description": "《一个女人一生中的二十四小时》这个集子收录了十三篇茨威格不同时期的作品。作为弗洛伊德的好友，他的作品将心理分析理论得到最完美的应用。在他的笔下，人物不再是单..."},
{"name": "茨威格小说集:全3册", "url": "https://book.douban.com/subject/1466231/", "comment_num": 183, "sub_tag_name": "茨威格", "tag_name": "文学", "score": 9.5, "book_id": "1466231", "description": null},
{"name": "与魔鬼作斗争", "url": "https://book.douban.com/subject/1035997/", "comment_num": 254, "sub_tag_name": "茨威格", "tag_name": "文学", "score": 8.8, "book_id": "1035997", "description": "简介《与魔鬼作斗争》论述了三位作家荷尔德林、克莱斯特和尼采的生活历程，他们都具有强烈的精神导师倾向，在生活中总是从精神上苛求自己，追求人类精神自由、完美的..."},
{"name": "永不安宁的心", "url": "https://book.douban.com/subject/1004063/", "comment_num": 285, "sub_tag_name": "茨威格", "tag_name": "文学", "score": 9.1, "book_id": "1004063", "description": "他，就在你心中最感动的地方，茨威格，被高尔基誉为“世界上最了解女人的作家”。他的“那种惊人诚挚的笔调，那片对于女人的超人的温存，那派对于主题的独创性，以及只..."},
{"name": "象棋的故事", "url": "https://book.douban.com/subject/20273057/", "comment_num": 747, "sub_tag_name": "茨威格", "tag_name": "文学", "score": 9.0, "book_id": "20273057", "description": "茨威格的代表作之一，讲述第二次世界大战期间，在一艘自美国开往阿根廷的轮船上，一个神秘的陌生人因偶然机会与国际象棋世界冠军琴多维奇对弈，居然轻易地赢了他。可就..."},
{"name": "一个陌生女人的来信", "url": "https://book.douban.com/subject/25751749/", "comment_num": 337, "sub_tag_name": "茨威格", "tag_name": "文学", "score": 8.8, "book_id": "25751749", "description": "《一个陌生女人的来信》讲述的是一个陌生的女人，在她生命的最后时刻，饱蘸一生的痴情，写下了一封凄婉动人的长信，向一位著名的作家袒露了自己绝望的爱慕之情。小说以..."},
{"name": "一颗心的沦亡", "url": "https://book.douban.com/subject/3028929/", "comment_num": 228, "sub_tag_name": "茨威格", "tag_name": "文学", "score": 8.8, "book_id": "3028929", "description": "《一颗心的沦亡:茨威格小说选》选录了茨威格中短篇小说十一篇，这些不同风格的作品代表了茨威格不同时期的艺术成就。茨威格以细腻的笔调展现了人物复杂幽暗的内心世界..."},
{"name": "世界建筑师", "url": "https://book.douban.com/subject/2114474/", "comment_num": 64, "sub_tag_name": "茨威格", "tag_name": "文学", "score": 8.6, "book_id": "2114474", "description": "《世界建筑师》内容简介：茨威格把\"精炼、浓缩和准确\"作为自己传记创作的准则，但他并不稽古抉微，旁征博引，露才扬己，而是如他自己所说的\"不是出之文献资料，而是..."},
{"name": "茨威格在巴西", "url": "https://book.douban.com/subject/10763919/", "comment_num": 101, "sub_tag_name": "茨威格", "tag_name": "文学", "score": 8.1, "book_id": "10763919", "description": "荣登法国《快报》图书畅销榜三个月之久天使湾文学奖获奖作品被法国著名导演吉拉尔•吉拉斯改编成戏剧在蒙帕纳斯剧院上演斯蒂芬•茨威格的爱与死之歌作为一位犹..."},
{"name": "艾利卡·埃瓦尔德之恋", "url": "https://book.douban.com/subject/26828750/", "comment_num": 51, "sub_tag_name": "茨威格", "tag_name": "文学", "score": 8.6, "book_id": "26828750", "description": "-当今拥有读者最多、最受读者喜爱的奥地利籍德语作家-打开弗洛伊德危险闸门的心灵猎手，以冰冷的诗意书写隐秘的激情-《艾利卡•埃瓦尔德之恋》：爱情最初的光辉..."},
{"name": "茨威格文集（全7卷）", "url": "https://book.douban.com/subject/1039237/", "comment_num": 101, "sub_tag_name": "茨威格", "tag_name": "文学", "score": 9.1, "book_id": "1039237", "description": "陕西人民出版社出的茨威格文集是七卷本，高中甫编。高中甫以前也编过一个茨威格的文集，但没有陕西人民出版社的这个齐。这个集子前三卷是小说卷（几乎收了他的全部..."},
{"name": "茨威格小说全集", "url": "https://book.douban.com/subject/1786011/", "comment_num": 165, "sub_tag_name": "茨威格", "tag_name": "文学", "score": 9.3, "book_id": "1786011", "description": "茨威格小说全集，ISBN：9787805942285，作者：（奥）斯·茨威格（StefanZweig）著；高中甫主编"},
{"name": "斯蒂芬·茨威格小说四篇", "url": "https://book.douban.com/subject/1825588/", "comment_num": 124, "sub_tag_name": "茨威格", "tag_name": "文学", "score": 9.3, "book_id": "1825588", "description": "收《家庭女教师》、《一个陌生女人的来信》、《看不见的珍藏》以及《象棋的故事》四部作品。"},
{"name": "茨威格中短篇小说经典", "url": "https://book.douban.com/subject/19966302/", "comment_num": 89, "sub_tag_name": "茨威格", "tag_name": "文学", "score": 9.1, "book_id": "19966302", "description": "●《一个陌生女人的来信》《一颗心的沦亡》《象棋的故事》……●茨威格的故事着力对隐秘的情感描写，直抵读者心灵，有着让人欲罢不能的魔力●高中甫主译，陆智..."},
{"name": "斯·茨威格小说选", "url": "https://book.douban.com/subject/1963728/", "comment_num": 238, "sub_tag_name": "茨威格", "tag_name": "文学", "score": 9.4, "book_id": "1963728", "description": "家庭女教师；夜色朦胧；保守不住的秘密；恐惧；马来狂人；一个陌生女人的来信；一个女人一生中的二十四小时；月光胡同；看不见的珍藏；象棋的故事...."},
{"name": "托尔斯泰传", "url": "https://book.douban.com/subject/3675518/", "comment_num": 51, "sub_tag_name": "茨威格", "tag_name": "文学", "score": 8.4, "book_id": "3675518", "description": "《托尔斯泰传》是奥地利著名作家茨威格的传记作品，描写了一代文学巨匠托尔斯泰生命最后三十年的心路历程和人生遭遇，真实地再现了托尔斯泰最后的人生是如何悲壮地落幕..."},
{"name": "罗曼·罗兰传", "url": "https://book.douban.com/subject/1138765/", "comment_num": 88, "sub_tag_name": "茨威格", "tag_name": "文学", "score": 8.3, "book_id": "1138765", "description": "《罗曼·罗兰传》内容简介：我们曾经敬奉之至的多少座丰碑都已坍塌破碎，被动荡夷为平地；罗曼·罗兰树起的丰碑却挺过枪林弹雨，穿过唇枪舌剑，傲然屹立。他的作品是人..."},
{"name": "一个陌生女人的来信", "url": "https://book.douban.com/subject/1320521/", "comment_num": 869, "sub_tag_name": "茨威格", "tag_name": "文学", "score": 8.9, "book_id": "1320521", "description": "本书收入茨威格最经典的中短篇小说，包括《家庭女教师》、《夜色朦胧》、《马来狂人》、《一个陌生女人的来信》、《女人和大地》、《一个女人一生中的二十四小时》等。..."},
{"name": "茨威格传记精华――六大师", "url": "https://book.douban.com/subject/1049476/", "comment_num": 45, "sub_tag_name": "茨威格", "tag_name": "文学", "score": 8.8, "book_id": "1049476", "description": "《六大师》是茨威格描写巴尔扎克、狄更斯、陀思妥耶夫斯基的《三大师》和描写荷尔德林、克莱斯特、尼采的《与恶魔的搏斗》两部传记的合集，是茨威格最具代表性、也是为..."},
{"name": "犹太人的命运", "url": "https://book.douban.com/subject/3931477/", "comment_num": 177, "sub_tag_name": "茨威格", "tag_name": "文学", "score": 8.2, "book_id": "3931477", "description": "《犹太人的命运:茨威格的心灵世界》内容为：“读历史不能深信不疑，而是应当好奇般地加以怀疑，因为看来是铁面无私的历史依就屈从于人类对传奇和神话的强烈爱好——它..."},
{"name": "一个古老的梦", "url": "https://book.douban.com/subject/1037991/", "comment_num": 146, "sub_tag_name": "茨威格", "tag_name": "文学", "score": 8.2, "book_id": "1037991", "description": ""},
{"name": "马来狂人", "url": "https://book.douban.com/subject/21335414/", "comment_num": 250, "sub_tag_name": "茨威格", "tag_name": "文学", "score": 8.5, "book_id": "21335414", "description": null},
{"name": "象棋的故事", "url": "https://book.douban.com/subject/1049193/", "comment_num": 157, "sub_tag_name": "茨威格", "tag_name": "文学", "score": 9.2, "book_id": "1049193", "description": null},
{"name": "回归自我", "url": "https://book.douban.com/subject/3583519/", "comment_num": 65, "sub_tag_name": "茨威格", "tag_name": "文学", "score": 8.7, "book_id": "3583519", "description": "《回归自我》主要内容：对每一个他自己说出的“不”断然说“是”，又对每一个“是”说“不”。他充分伸展着自身，以尽力拉开他本性中的两极，将这两极间的电压当作真正..."},
{"name": "象棋的故事", "url": "https://book.douban.com/subject/1210503/", "comment_num": 81, "sub_tag_name": "茨威格", "tag_name": "文学", "score": 9.3, "book_id": "1210503", "description": ""},
{"name": "夜色朦胧", "url": "https://book.douban.com/subject/1068151/", "comment_num": 237, "sub_tag_name": "茨威格", "tag_name": "文学", "score": 8.6, "book_id": "1068151", "description": "在一九一零年至一九―一年之间，茨威格发表了许多作品：一九零六年完成的中篇小说《猩红热》，一九零七年完成的中篇小说《家庭女教师》，还有中篇小说《燃烧的秘密》、..."},
{"name": "一个陌生女人的来信", "url": "https://book.douban.com/subject/11444363/", "comment_num": 329, "sub_tag_name": "茨威格", "tag_name": "文学", "score": 8.4, "book_id": "11444363", "description": "一个陌生女人的来信：茨威格中短篇小说选，ISBN：9787542935007，作者：（奥）茨威格（Zweig，S.）著"},
{"name": "灼人的秘密", "url": "https://book.douban.com/subject/3040515/", "comment_num": 251, "sub_tag_name": "茨威格", "tag_name": "文学", "score": 9.0, "book_id": "3040515", "description": "灼人的秘密--（奥地利）茨威格海边的恋情--（波兰）显克微奇思想--（俄国）安德列耶夫卡尔美拉（意大利）亚米契斯卡斯特罗修道院院长（法国）司汤达"},
{"name": "精神疗法", "url": "https://book.douban.com/subject/1291477/", "comment_num": 73, "sub_tag_name": "茨威格", "tag_name": "文学", "score": 8.5, "book_id": "1291477", "description": "茨威格的不朽名著:《精神療法》一書,是分別以馳名世界的三個精神學先驅——梅爾梅斯、瑪麗．貝克爾、弗洛伊德的一生對人的精神現象的摸索、樸素的實驗，以及對「患..."},
{"name": "茨威格情欲小说", "url": "https://book.douban.com/subject/10603708/", "comment_num": 157, "sub_tag_name": "茨威格", "tag_name": "文学", "score": 8.5, "book_id": "10603708", "description": "“新文艺外国文学大师读本”初版于上世纪九十年代，深受广大读者喜爱。今年适逢上海文艺出版社建社六十周年，我们重新整理出版这套丛书，奉献给新一代的读者。..."},
{"name": "邂逅人与书籍", "url": "https://book.douban.com/subject/25857441/", "comment_num": 37, "sub_tag_name": "茨威格", "tag_name": "文学", "score": 8.4, "book_id": "25857441", "description": "《邂逅人与书籍：茨威格读书随笔》是茨威格的文学评论集，包括作家介绍、作品评论、讲演、纪念文章、序言等不同体裁，论及世界文学史上许多伟大的作家，如卢梭、巴尔扎..."},
{"name": "描述自我的三作家", "url": "https://book.douban.com/subject/1263270/", "comment_num": 60, "sub_tag_name": "茨威格", "tag_name": "文学", "score": 8.3, "book_id": "1263270", "description": "在这本书中，斯台芬·茨威格从世界文坛上选择了三个作家作为他研究的对象。他们是意大利作家卡萨诺瓦、法国作家司汤达和俄国作家托尔斯泰。在本书中，斯台芬·茨威格是..."},
{"name": "茨威格散文", "url": "https://book.douban.com/subject/3272471/", "comment_num": 138, "sub_tag_name": "茨威格", "tag_name": "文学", "score": 8.4, "book_id": "3272471", "description": "斯台芬·茨威格作为小说家和传记作家早已风靡中国，享有盛名，但他的散文，包括评论、演讲和书信还介绍得不多，而这些文章恰好可以让我们看到茨威格的性格特点、社交往..."},
{"name": "外国中短篇小说藏本·茨威格", "url": "https://book.douban.com/subject/4320859/", "comment_num": 185, "sub_tag_name": "茨威格", "tag_name": "文学", "score": 8.9, "book_id": "4320859", "description": "《外国中短篇小说藏本:茨威格》内容简介：在我们熟悉的外国文学名家中，很多都创作有中短篇小说佳作，更有的是专以中短篇小说享有盛誉。外国中短篇小说中的精品佳作，..."},
{"name": "火烧火燎的秘密里昂的婚礼", "url": "https://book.douban.com/subject/1101912/", "comment_num": 98, "sub_tag_name": "茨威格", "tag_name": "文学", "score": 8.6, "book_id": "1101912", "description": "《里昂的婚礼》是茨威格的一部短篇小说，它演奏了法国大革命血雨腥风的日子里一部凄美动人的恋曲。在作者简洁的笔触下法国大革命红色恐怖的触目惊心的画面跃然纸上。这..."},
{"name": "权与欲的狂飙", "url": "https://book.douban.com/subject/1392592/", "comment_num": 127, "sub_tag_name": "茨威格", "tag_name": "文学", "score": 8.4, "book_id": "1392592", "description": "《权与欲的狂飙:玛丽·斯图亚特(最新版插图版)》是奥地利著名作家斯蒂芬·茨威格最具影响力的传记作品，对苏格兰女王玛丽·斯图亚特的一生做了深入细致的开掘，既充..."},
{"name": "一个女人的24小时", "url": "https://book.douban.com/subject/1388331/", "comment_num": 67, "sub_tag_name": "茨威格", "tag_name": "文学", "score": 8.6, "book_id": "1388331", "description": null},
{"name": "一个陌生女人的来信", "url": "https://book.douban.com/subject/2066417/", "comment_num": 509, "sub_tag_name": "茨威格", "tag_name": "文学", "score": 8.6, "book_id": "2066417", "description": "《一个陌生女人的来信》是具有国际声誉的奥地利小说家、传记作家茨威格最著名的短篇小说之一，也是世界文学史上最负盛誉的经典爱情小说之一。该小说曾多次被搬上银幕，..."},
{"name": "茨威格短篇小说选", "url": "https://book.douban.com/subject/3074105/", "comment_num": 67, "sub_tag_name": "茨威格", "tag_name": "文学", "score": 9.0, "book_id": "3074105", "description": "这部小说集选择了脍炙人口的《家庭女教师》、《掩盖不住的秘密》、《看不见的珍藏》等。此外还从《人类星光灿烂的时刻》中选择了《拜占庭的陷落》、《滑铁卢震撼世界的..."},
{"name": "一颗心的沦亡", "url": "https://book.douban.com/subject/26118434/", "comment_num": 43, "sub_tag_name": "茨威格", "tag_name": "文学", "score": 9.1, "book_id": "26118434", "description": "《一颗心的沦亡》茨威格的作品擅长细致的性格刻画，以及对奇特命运下个人遭遇和心灵的描摹，尤其善于在激情的煎熬中洞察女性内心活动。本书收录二十余篇短篇名作，如《..."},
{"name": "一个陌生女人的来信", "url": "https://book.douban.com/subject/25895962/", "comment_num": 71, "sub_tag_name": "茨威格", "tag_name": "文学", "score": 9.0, "book_id": "25895962", "description": "本书为茨威格中篇小说集，《一个陌生女人的来信》讲述一位男子在四十一岁生日当天收到一封厚厚的没有署名的信，信出自一位临终女子之手，字里行间是她对他十八年刻骨铭..."},
{"name": "茨威格文学代表作", "url": "https://book.douban.com/subject/1925129/", "comment_num": 145, "sub_tag_name": "茨威格", "tag_name": "文学", "score": 9.0, "book_id": "1925129", "description": "一、中短篇小说生命的奇迹（桑仁/译（较差）灼人的秘密（韩耀成高中甫/译）热带癫狂症患者（张敬铭/译杜文裳/校）一个陌生女人的来信（韩耀成/译）..."},
{"name": "一个陌生女人的来信", "url": "https://book.douban.com/subject/1661334/", "comment_num": 282, "sub_tag_name": "茨威格", "tag_name": "文学", "score": 8.8, "book_id": "1661334", "description": null},
{"name": "一个陌生女人的来信", "url": "https://book.douban.com/subject/11637640/", "comment_num": 331, "sub_tag_name": "茨威格", "tag_name": "文学", "score": 9.0, "book_id": "11637640", "description": "《一个陌生女人的来信》是茨威格最具代表性的作品之一。《一个陌生女人的来信》描写一个男子在四十一岁生日当天收到一封没有署名和地址的信，信中一个临死的女人讲述了..."},
{"name": "危险的怜悯", "url": "https://book.douban.com/subject/3080219/", "comment_num": 29, "sub_tag_name": "茨威格", "tag_name": "文学", "score": 8.7, "book_id": "3080219", "description": null},
{"name": "茨威格读本", "url": "https://book.douban.com/subject/20444098/", "comment_num": 64, "sub_tag_name": "茨威格", "tag_name": "文学", "score": 8.7, "book_id": "20444098", "description": "《外国文学大师读本丛书：茨威格读本》收入茨威格最为脍炙人口的中短篇小说《一个陌生女人的来信》、《一个女人一生中的二十四小时》、《象棋的故事》，传记《良心反抗..."},
{"name": "茨威格中短篇小说选", "url": "https://book.douban.com/subject/2005555/", "comment_num": 149, "sub_tag_name": "茨威格", "tag_name": "文学", "score": 9.3, "book_id": "2005555", "description": "《茨威格:中短篇小说选》打破传统的插图形式，将作家与作品、历史与现实有机地链接。大量珍贵的图片，展示历史风貌，评析作品　特色，揭示作家个性。茨威格受他朋友弗..."},
{"name": "人类命运攸关的时辰", "url": "https://book.douban.com/subject/2055745/", "comment_num": 23, "sub_tag_name": "茨威格", "tag_name": "文学", "score": 9.2, "book_id": "2055745", "description": "人类命运攸关的时辰：德语文学精品读（德汉对照），ISBN：9787310026142，作者：斯蒂芬.茨威格"},
{"name": "一个陌生女人的来信", "url": "https://book.douban.com/subject/26256868/", "comment_num": 137, "sub_tag_name": "茨威格", "tag_name": "文学", "score": 9.0, "book_id": "26256868", "description": "《一个陌生女人的来信：茨威格小说菁华集》是奥地利著名作家茨威格的代表作之一。其中最有名的是《一个陌生女人的来信》，讲述一个陌生的女人，在她生命的最后时刻写给..."},
{"name": "一个陌生女人的来信", "url": "https://book.douban.com/subject/10760907/", "comment_num": 86, "sub_tag_name": "茨威格", "tag_name": "文学", "score": 9.0, "book_id": "10760907", "description": null},
{"name": "一个陌生女人的来信", "url": "https://book.douban.com/subject/26606495/", "comment_num": 95, "sub_tag_name": "茨威格", "tag_name": "文学", "score": 8.6, "book_id": "26606495", "description": "《一个陌生女人的来信》是由奥地利的著名作家茨威格创作的，是其代表作之一，讲述的是一个陌生的女人，在她生命的最后时刻，饱蘸着一生的痴情，写下了一封凄婉动人的长..."},
{"name": "一个陌生女人的来信", "url": "https://book.douban.com/subject/26365979/", "comment_num": 140, "sub_tag_name": "茨威格", "tag_name": "文学", "score": 8.9, "book_id": "26365979", "description": "《一个陌生女人的来信》、《一个女人生活中的二十四小时》这两篇小说以不同的方式展现意识流小说的特点，重在心理分析。C夫人的叙述和陌生女人的长信都是自我宣泄、披..."},
{"name": "DecisiveMomentsinHistory", "url": "https://book.douban.com/subject/2227346/", "comment_num": 16, "sub_tag_name": "茨威格", "tag_name": "文学", "score": 8.9, "book_id": "2227346", "description": "Thefactorsthatdictateandchangethecourseofhistoryareprimarilythepr..."},
{"name": "茨威格评传", "url": "https://book.douban.com/subject/1971117/", "comment_num": 87, "sub_tag_name": "茨威格", "tag_name": "文学", "score": 7.8, "book_id": "1971117", "description": "《茨威格评传:伟大心灵的回声》是高等教育出版社《学思丛书》之一。奥地利著名作家斯台芬·茨威格的心理分析，对人们灵魂的发掘与刻画，小说浓郁的抒情性和人物传记强..."},
{"name": "为爱疯狂", "url": "https://book.douban.com/subject/1118817/", "comment_num": 44, "sub_tag_name": "茨威格", "tag_name": "文学", "score": 8.5, "book_id": "1118817", "description": null},
{"name": "茨威格精选集", "url": "https://book.douban.com/subject/1099460/", "comment_num": 198, "sub_tag_name": "茨威格", "tag_name": "文学", "score": 9.0, "book_id": "1099460", "description": "茨威格的小说深受弗洛伊德的影响。弗洛伊德在治疗精神病人的过程中，提出了心理分析法。根据弗洛伊的观点，人的思维不仅有意识，还有前意识和无意识。茨威格不仅写过大..."},
{"name": "大探险家", "url": "https://book.douban.com/subject/1017465/", "comment_num": 28, "sub_tag_name": "茨威格", "tag_name": "文学", "score": 9.1, "book_id": "1017465", "description": "本书收入奥地利名作家茨威格（1881－1942）的两种重要传记：《麦哲伦》和《亚美利戈》。《麦哲伦》以饱蘸激情的文字描述了麦哲伦进行环球探险的千难万险以..."},
{"name": "良心反对暴力", "url": "https://book.douban.com/subject/1921079/", "comment_num": 34, "sub_tag_name": "茨威格", "tag_name": "文学", "score": 8.9, "book_id": "1921079", "description": null},
{"name": "里昂的婚礼", "url": "https://book.douban.com/subject/3806575/", "comment_num": 99, "sub_tag_name": "茨威格", "tag_name": "文学", "score": 8.9, "book_id": "3806575", "description": "收入茨威格的《里昂的婚礼》、《象棋的故事》、《看不见的珍藏》和《一个陌生女人的来信》4篇力作。"},
{"name": "世界十大中短篇小说家：茨威格", "url": "https://book.douban.com/subject/25866060/", "comment_num": 29, "sub_tag_name": "茨威格", "tag_name": "文学", "score": 9.3, "book_id": "25866060", "description": null},
{"name": "一个陌生女人的来信", "url": "https://book.douban.com/subject/6538431/", "comment_num": 302, "sub_tag_name": "茨威格", "tag_name": "文学", "score": 9.1, "book_id": "6538431", "description": "《译美文:一个陌生女人的来信》内容简介：一个男子在41岁生日当天收到一封没有署名和地址的信，这封信出自一个临死的女人，讲述了一相刻骨铭心的爱情故事，而这个故..."},
{"name": "茨威格散文选", "url": "https://book.douban.com/subject/1257029/", "comment_num": 102, "sub_tag_name": "茨威格", "tag_name": "文学", "score": 8.4, "book_id": "1257029", "description": "茨威格是一位充满人道主义激情的著名作家，他思想深邃，感情丰富，目光敏锐，笔触细腻。他非常善于对一些重大的社会题材和历史事件进行独到的观察和独特的描述，他尤其..."},
{"name": "TheImpossibleExile", "url": "https://book.douban.com/subject/25872220/", "comment_num": 10, "sub_tag_name": "茨威格", "tag_name": "文学", "score": 0.0, "book_id": "25872220", "description": null},
{"name": "ChessStory", "url": "https://book.douban.com/subject/1767101/", "comment_num": 24, "sub_tag_name": "茨威格", "tag_name": "文学", "score": 9.3, "book_id": "1767101", "description": "ChessStory,alsoknownasTheRoyalGame,istheAustrianmasterStefanZw..."},
{"name": "茨威格作品精选", "url": "https://book.douban.com/subject/3100746/", "comment_num": 72, "sub_tag_name": "茨威格", "tag_name": "文学", "score": 9.2, "book_id": "3100746", "description": "《茨威格作品精选(插图本)》是茨威格作品精选集，书中具体收录了：《灼人的秘密》、《猩红热》、《一个陌生女人的来信》、《热带癫狂症患者》、《象棋的故事》、《拜..."},
{"name": "银弦集・早年的花环・新的旅程", "url": "https://book.douban.com/subject/1021413/", "comment_num": 27, "sub_tag_name": "茨威格", "tag_name": "文学", "score": 7.8, "book_id": "1021413", "description": "早在中学时代，茨威格便开始写诗。从一九零一年二月《银弦集》在维也纳出版，诗人茨威格一生写过许多优美的诗歌。本书收录了《银弦集》《早年的花环》和《新的旅程》三..."},
{"name": "JourneyIntothePast", "url": "https://book.douban.com/subject/5033213/", "comment_num": 12, "sub_tag_name": "茨威格", "tag_name": "文学", "score": 7.4, "book_id": "5033213", "description": null},
{"name": "狐狸", "url": "https://book.douban.com/subject/1208898/", "comment_num": 68, "sub_tag_name": "茨威格", "tag_name": "文学", "score": 7.9, "book_id": "1208898", "description": "本书是奥地利著名作家，斯台芬·茨威格的一部讽刺喜剧，讲述了渥尔波涅这只老狐狸为富不仁。他假装生病，似乎命在旦夕。那些觊觎他巨额财产的人纷纷前来探望，希望在他..."},
{"name": "三人书简", "url": "https://book.douban.com/subject/1898593/", "comment_num": 28, "sub_tag_name": "茨威格", "tag_name": "文学", "score": 8.5, "book_id": "1898593", "description": "本书收集了苏联作家髙尔基和法国作家罗曼•罗兰、奥地利作家茨威格的部分往来书信、电文，是一部外国书信体文学的范本。由于三位作家在往来书简中多次谈及了以下四篇佳..."},
{"name": "一个陌生女人的来信", "url": "https://book.douban.com/subject/6535064/", "comment_num": 108, "sub_tag_name": "茨威格", "tag_name": "文学", "score": 8.5, "book_id": "6535064", "description": "《世界文学名著典藏:一个陌生女人的来信(全译插图本)》讲述了：一个陌生的女人，在她生命的最后时刻，饱蘸着一生的痴情，写下了一封凄婉动人的长信，向一位著名的作..."},
{"name": "爱与同情", "url": "https://book.douban.com/subject/3089027/", "comment_num": 10, "sub_tag_name": "茨威格", "tag_name": "文学", "score": 8.6, "book_id": "3089027", "description": null},
{"name": "书的礼赞", "url": "https://book.douban.com/subject/1066490/", "comment_num": 98, "sub_tag_name": "茨威格", "tag_name": "文学", "score": 7.8, "book_id": "1066490", "description": "本书辑录的八篇散文，均出自名家之手。旁征博引，说古论今，漫谈书的美好价值、书的敌人和灾难、书的保护和珍藏等等。译者叶灵凤（19O4一1975）是现代著名画家..."},
{"name": "秘密的事情", "url": "https://book.douban.com/subject/1073267/", "comment_num": 16, "sub_tag_name": "茨威格", "tag_name": "文学", "score": 7.7, "book_id": "1073267", "description": "斯蒂芬·茨威格，世界著名德语作家；理查·施特劳斯，德国著名作曲家兼指挥家。是什么样的契机将这两位文化巨擘联系了起来，使两个在1931-1935年间互相信件往..."},
{"name": "看不见的收藏(德汉对照分级读物)", "url": "https://book.douban.com/subject/1242263/", "comment_num": 92, "sub_tag_name": "茨威格", "tag_name": "文学", "score": 8.7, "book_id": "1242263", "description": "本书收录了奥地利著名作家茨威格的三篇中篇小说，从中我们可以感受到他那细致入微的心理刻画，以及对人物性格的精彩分析。《日内瓦湖的故事》描述了一个从法国战俘营..."},
{"name": "一个陌生女人的来信", "url": "https://book.douban.com/subject/1559491/", "comment_num": 136, "sub_tag_name": "茨威格", "tag_name": "文学", "score": 8.8, "book_id": "1559491", "description": "奥地利作家斯特凡·茨威格（1881—1942）的名字中国读者已经很熟悉了。这本小说集共收茨威格的中、短篇小说12篇，其中《灼人的秘密》、《一个陌生女人的来信..."},
{"name": "LetterfromanUnknownWomanandOtherStories", "url": "https://book.douban.com/subject/20145547/", "comment_num": 36, "sub_tag_name": "茨威格", "tag_name": "文学", "score": 9.0, "book_id": "20145547", "description": "ThesefourStefanZweigstoriesnewlytranslatedbytheaward-winningAntheaB..."},
{"name": "茨威格传记精华――罗曼・罗兰", "url": "https://book.douban.com/subject/1016247/", "comment_num": 22, "sub_tag_name": "茨威格", "tag_name": "文学", "score": 8.3, "book_id": "1016247", "description": "奥地利大作家斯苔芬・茨威格（1881－1942）擅长写传记作品，有《三大师》、《三诗人》等精典之作传世。他与罗曼・罗兰熟识，且私交甚笃，本书是他满怀深情之作..."},
{"name": "玛丽亚.斯图亚特", "url": "https://book.douban.com/subject/1120817/", "comment_num": 32, "sub_tag_name": "茨威格", "tag_name": "文学", "score": 8.0, "book_id": "1120817", "description": null},
{"name": "一个陌生女子的来信", "url": "https://book.douban.com/subject/1072213/", "comment_num": 396, "sub_tag_name": "茨威格", "tag_name": "文学", "score": 8.7, "book_id": "1072213", "description": "《一个陌生女子的来信》讲述了一个女人一生中惟一的一次情感历程，从未成年的小女孩到花样年华的少女到风姿绰约的成熟女人再到——临终时才允许灵魂呼喊一次的生命垂危..."},
{"name": "斯.茨威格小说选", "url": "https://book.douban.com/subject/3191193/", "comment_num": 91, "sub_tag_name": "茨威格", "tag_name": "文学", "score": 9.0, "book_id": "3191193", "description": "家庭女教师　　　　　　　　张玉书译夜色朦胧　　　　　　　　　张玉书译保守不住的秘密　　　　　　　涛声译恐惧　　　　　　　　　　　赵登荣译马来狂人　　..."},
{"name": "一个人的传奇", "url": "https://book.douban.com/subject/1208900/", "comment_num": 43, "sub_tag_name": "茨威格", "tag_name": "文学", "score": 7.7, "book_id": "1208900", "description": "本书是奥地利著名作家斯台芬·茨威格的一部戏剧作品，讲述了一位著名作家和他儿子的故事。《一个人的传奇》既非古典意义上的悲剧，亦非揭露家庭罪恶的自然主..."},
{"name": "一个陌生女人的来信", "url": "https://book.douban.com/subject/4051532/", "comment_num": 81, "sub_tag_name": "茨威格", "tag_name": "文学", "score": 8.2, "book_id": "4051532", "description": "《一个陌生女人的来信》讲述的是一个陌生的女人，在她生命的最后时刻，饱蘸着一生的痴情，写下了一封凄婉动人的长信，向一位著名的作家袒露了自己绝望的爱慕之情。故事..."},
{"name": "一个陌生女人的来信", "url": "https://book.douban.com/subject/1059216/", "comment_num": 126, "sub_tag_name": "茨威格", "tag_name": "文学", "score": 8.8, "book_id": "1059216", "description": "一个陌生女人的来信…………（1）夏天的故事……………………（39）家庭教师………………………（51）生命的奇迹……………………（67）艾利卡·埃瓦尔..."},
{"name": "罗曼.罗兰", "url": "https://book.douban.com/subject/22685932/", "comment_num": 10, "sub_tag_name": "茨威格", "tag_name": "文学", "score": 7.4, "book_id": "22685932", "description": null},
{"name": "一个陌生女人的来信", "url": "https://book.douban.com/subject/4880389/", "comment_num": 77, "sub_tag_name": "茨威格", "tag_name": "文学", "score": 9.0, "book_id": "4880389", "description": "《一个陌生女人的来信:茨威格小说精选》共收入其经典作品十篇，包括有被遗忘的梦、生命的奇迹、灼人的秘密、一个陌生女人的来信、一颗心的沦亡等。茨威格是弗洛伊德的..."},
{"name": "人文之光", "url": "https://book.douban.com/subject/1001095/", "comment_num": 10, "sub_tag_name": "茨威格", "tag_name": "文学", "score": 7.8, "book_id": "1001095", "description": "奥地利作家斯苔芬・茨威格（1881－1942）的传记作品闻名遐迩，独具特色。本书收入了他的两篇作品：《伊拉斯谟的成功与悲剧》和《托尔斯泰》。伊拉斯谟（1..."},
{"name": "象棋的故事·看不见的珍藏", "url": "https://book.douban.com/subject/1101910/", "comment_num": 126, "sub_tag_name": "茨威格", "tag_name": "文学", "score": 9.3, "book_id": "1101910", "description": "《象棋的故事看不见的珍藏》(德汉对照)这中短篇小说直接真实地反映了奥地利在一战之后世界经济危机的影响下产生的通货膨胀带给老百性的害难性后果。茨威格形象地描述..."},
{"name": "文武之道", "url": "https://book.douban.com/subject/1013384/", "comment_num": 10, "sub_tag_name": "茨威格", "tag_name": "文学", "score": 0.0, "book_id": "1013384", "description": "斯苔芬・茨威格（1881－1942），奥地利著名作家，以心理分析小说和传记创作在全世界享有盛誉，本书收入了其重要传记作品《司汤达》和《约瑟夫・福歇》。..."},
{"name": "一个女人一生中的二十四小时", "url": "https://book.douban.com/subject/3090667/", "comment_num": 14, "sub_tag_name": "茨威格", "tag_name": "文学", "score": 7.9, "book_id": "3090667", "description": null},
{"name": "海滨之屋", "url": "https://book.douban.com/subject/1208899/", "comment_num": 40, "sub_tag_name": "茨威格", "tag_name": "文学", "score": 8.0, "book_id": "1208899", "description": "本书是奥地利著名作家斯台芬·茨威格的一部戏剧作品，讲述了十八世纪德国某港口城市的领港员哥特霍尔特·克吕格在家里开了一家酒店。就在这座“海滨之屋”里，演出了一..."},
{"name": "麦哲伦航海纪", "url": "https://book.douban.com/subject/1083446/", "comment_num": 300, "sub_tag_name": "茨威格", "tag_name": "文学", "score": 8.7, "book_id": "1083446", "description": "本书以大量精彩的历史图片再现了费尔南多·麦哲利约什的英雄业绩：一个孤独的英雄为了能像哥伦布等人那样“惊天动地”，密谋策划寻找传闻中欧洲通往亚洲香料群岛的海..."},
{"name": "茨威格画传", "url": "https://book.douban.com/subject/6852590/", "comment_num": 26, "sub_tag_name": "茨威格", "tag_name": "文学", "score": 7.3, "book_id": "6852590", "description": "《茨威格画传》是我国著名翻译家高中甫先生最近的力作，以优美的文笔和翔实的资料勾勒出了茨威格传奇的一生，尤其是全书收入了200多幅有关茨威格的珍贵照片，是国内..."},
{"name": "茨威格中短篇小说叙事研究", "url": "https://book.douban.com/subject/6889896/", "comment_num": 10, "sub_tag_name": "茨威格", "tag_name": "文学", "score": 0.0, "book_id": "6889896", "description": "《茨威格中短篇小说叙事研究》先以时间顺序为纵轴，选取各个时期的四篇代表作予以分析；再在横轴上按照四个主题——心理表现、自杀，空间描写及女性形象来概括出茨威格..."},
{"name": "巫山云", "url": "https://book.douban.com/subject/3044944/", "comment_num": 10, "sub_tag_name": "茨威格", "tag_name": "文学", "score": 0.0, "book_id": "3044944", "description": "巫山云是茨威格的小说《一个陌生女人的来信》的别名。《一封陌生女子的来信》不仅是茨威格小说中的璀璨明珠，也是世界文学宝库中罕见的珍奇瑰宝。这篇小说问世之后，几..."},
{"name": "鹿特丹的伊拉斯谟", "url": "https://book.douban.com/subject/26394190/", "comment_num": 117, "sub_tag_name": "茨威格", "tag_name": "文学", "score": 9.1, "book_id": "26394190", "description": "我几个月来像走投无路似的进行自我保护……我选择了鹿特丹的伊拉斯谟作为自己的救星。他中庸、明智，被夹在新教徒和天主教徒之间，恰似我们今天被夹在各种对立的政治运..."},
{"name": "麦哲伦的功绩", "url": "https://book.douban.com/subject/3320142/", "comment_num": 10, "sub_tag_name": "茨威格", "tag_name": "文学", "score": 0.0, "book_id": "3320142", "description": null},
{"name": "格里沙中士", "url": "https://book.douban.com/subject/1781452/", "comment_num": 10, "sub_tag_name": "茨威格", "tag_name": "文学", "score": 0.0, "book_id": "1781452", "description": null},
{"name": "感謝蒙田", "url": "https://book.douban.com/subject/3701121/", "comment_num": 10, "sub_tag_name": "茨威格", "tag_name": "文学", "score": 0.0, "book_id": "3701121", "description": "為了能真正讀懂蒙田，人們不可以太年輕，不可以沒有閱歷，不可以沒有種種失望。因為只有這樣的人才知道，在那些烏合之眾瘋狂的時代裡，要始終忠於最內在的自我，需要..."},
{"name": "茨威格传奇作品集", "url": "https://book.douban.com/subject/2365162/", "comment_num": 19, "sub_tag_name": "茨威格", "tag_name": "文学", "score": 7.8, "book_id": "2365162", "description": null},
{"name": "世界文学著名文库第一辑", "url": "https://book.douban.com/subject/1459745/", "comment_num": 44, "sub_tag_name": "茨威格", "tag_name": "文学", "score": 8.8, "book_id": "1459745", "description": "本丛书包括：《一个陌生女人的来信》、《鲁滨逊漂流记》、《双城记》、《汤姆·索亚历险记》、《莎士比亚喜剧集》、《爱玛》、《福尔摩斯探案集》、《呼啸山庄》等等。..."},
{"name": "一个女人一生之中的24小时（德语经典文学手绘插画本)", "url": "https://book.douban.com/subject/25813516/", "comment_num": 27, "sub_tag_name": "茨威格", "tag_name": "文学", "score": 7.6, "book_id": "25813516", "description": "该书属于“德语经典文学手绘插画本”系列丛书中的其中一本。茨威格（StephanZweig，1881-1942）是奥地利著名作家、小说家、传记作家，擅长..."},
{"name": "Marie-Antoinette", "url": "https://book.douban.com/subject/1940538/", "comment_num": 10, "sub_tag_name": "茨威格", "tag_name": "文学", "score": 0.0, "book_id": "1940538", "description": null},
{"name": "特西特斯", "url": "https://book.douban.com/subject/1013493/", "comment_num": 14, "sub_tag_name": "茨威格", "tag_name": "文学", "score": 7.7, "book_id": "1013493", "description": null},
{"name": "茨威格散文选", "url": "https://book.douban.com/subject/3931731/", "comment_num": 10, "sub_tag_name": "茨威格", "tag_name": "文学", "score": 0.0, "book_id": "3931731", "description": "《茨威格:散文选》收录了茨威格的散文代表作以及一些著名人物传记的精彩片断，珠玑璀璨，异彩灼人。茨威格是一位充满人道主义激情的著名作家，他思想深邃，感情丰富，..."},
{"name": "一封陌生女子的來信", "url": "https://book.douban.com/subject/1361908/", "comment_num": 15, "sub_tag_name": "茨威格", "tag_name": "文学", "score": 7.6, "book_id": "1361908", "description": null},
{"name": "一个女人一生中的二十四小时", "url": "https://book.douban.com/subject/26771221/", "comment_num": 11, "sub_tag_name": "茨威格", "tag_name": "文学", "score": 8.6, "book_id": "26771221", "description": null},
{"name": "ThePost-OfficeGirl", "url": "https://book.douban.com/subject/3212307/", "comment_num": 10, "sub_tag_name": "茨威格", "tag_name": "文学", "score": 0.0, "book_id": "3212307", "description": "Thepost-officegirlisChristine,wholooksafterherailingmotherandtoils..."},
{"name": "茨威格触摸人类的心灵", "url": "https://book.douban.com/subject/1062093/", "comment_num": 10, "sub_tag_name": "茨威格", "tag_name": "文学", "score": 0.0, "book_id": "1062093", "description": null},
{"name": "Lemonded'hier", "url": "https://book.douban.com/subject/6988362/", "comment_num": 10, "sub_tag_name": "茨威格", "tag_name": "文学", "score": 0.0, "book_id": "6988362", "description": null},
{"name": "归来没有统帅", "url": "https://book.douban.com/subject/2348558/", "comment_num": 10, "sub_tag_name": "茨威格", "tag_name": "文学", "score": 8.9, "book_id": "2348558", "description": null},
{"name": "麦哲伦传", "url": "https://book.douban.com/subject/1191019/", "comment_num": 24, "sub_tag_name": "茨威格", "tag_name": "文学", "score": 8.3, "book_id": "1191019", "description": "书本之所以产生，是由于有各种各样的情感需要表达。推动人们写书的，可以是一种灵感，也可以是一种谢忱；麦哲伦，著名航海家和探险家，第一个把环球航行理想付诸冒险运..."},
{"name": "茨威格幸福语录", "url": "https://book.douban.com/subject/21810821/", "comment_num": 10, "sub_tag_name": "茨威格", "tag_name": "文学", "score": 0.0, "book_id": "21810821", "description": "《茨威格幸福语录》尽最大努力呈现斯蒂芬·茨威格的智慧语言，希望广大读者朋友们能从中汲取精神的营养，获得灵魂的启迪，并把一些珍贵的道理运用于生活，祝愿各位今后..."},
{"name": "茨威格小说研究", "url": "https://book.douban.com/subject/1548196/", "comment_num": 32, "sub_tag_name": "茨威格", "tag_name": "文学", "score": 6.1, "book_id": "1548196", "description": "《茨威格小说研究》对这位奥地利文学大师的犹太出身、文学创作历程等进行人物分析，并对其小说作品进行文本研究，且从大师的细节描写、心理刻画等方面论述其艺术特色。..."},
{"name": "茨威格散文精选", "url": "https://book.douban.com/subject/1023538/", "comment_num": 26, "sub_tag_name": "茨威格", "tag_name": "文学", "score": 7.5, "book_id": "1023538", "description": ""},
{"name": "VierundzwanzigStundenausdemLebeneinerFrau", "url": "https://book.douban.com/subject/4122612/", "comment_num": 10, "sub_tag_name": "茨威格", "tag_name": "文学", "score": 0.0, "book_id": "4122612", "description": null},
{"name": "海涅席勒茨威格", "url": "https://book.douban.com/subject/3124035/", "comment_num": 10, "sub_tag_name": "茨威格", "tag_name": "文学", "score": 0.0, "book_id": "3124035", "description": "本书是作者过往在阅读和翻译过程中对相关人物研究或感悟的文章集合。"},
{"name": "通往心灵-茨威格其人其作", "url": "https://book.douban.com/subject/1059478/", "comment_num": 10, "sub_tag_name": "茨威格", "tag_name": "文学", "score": 0.0, "book_id": "1059478", "description": "...."},
{"name": "巴尔扎克", "url": "https://book.douban.com/subject/22685672/", "comment_num": 10, "sub_tag_name": "茨威格", "tag_name": "文学", "score": 0.0, "book_id": "22685672", "description": "本书共分为六卷,主要内容包括:青年时代与初露锋芒；巴尔扎克勤奋创作；巴尔扎克的生活小说；小说家巴尔扎克的光辉与苦难等."},
{"name": "Lettred'uneinconnue", "url": "https://book.douban.com/subject/4740126/", "comment_num": 14, "sub_tag_name": "茨威格", "tag_name": "文学", "score": 8.7, "book_id": "4740126", "description": null},
{"name": "巴尔扎克", "url": "https://book.douban.com/subject/1642816/", "comment_num": 10, "sub_tag_name": "茨威格", "tag_name": "文学", "score": 8.0, "book_id": "1642816", "description": ""},
{"name": "象棋的故事(文学小丛书)", "url": "https://book.douban.com/subject/3099173/", "comment_num": 78, "sub_tag_name": "茨威格", "tag_name": "文学", "score": 9.4, "book_id": "3099173", "description": null},
{"name": "BrazilLandoftheFuture", "url": "https://book.douban.com/subject/14611456/", "comment_num": 10, "sub_tag_name": "茨威格", "tag_name": "文学", "score": 0.0, "book_id": "14611456", "description": null},
{"name": "Schachnovelle", "url": "https://book.douban.com/subject/1999421/", "comment_num": 36, "sub_tag_name": "茨威格", "tag_name": "文学", "score": 9.0, "book_id": "1999421", "description": null},
{"name": "文豪笔下的文豪", "url": "https://book.douban.com/subject/1520008/", "comment_num": 10, "sub_tag_name": "茨威格", "tag_name": "文学", "score": 0.0, "book_id": "1520008", "description": "茨威格的小说深受弗洛伊德的影响。弗洛伊德在治疗精神病人的过程中，提出了心理分析法。根据弗洛伊的观点，人的思维不仅有意识，还有前意识和无意识。茨威格不仅写过大..."},
{"name": "无处为家", "url": "https://book.douban.com/subject/1400720/", "comment_num": 35, "sub_tag_name": "茨威格", "tag_name": "文学", "score": 7.7, "book_id": "1400720", "description": "为逃脱纳粹的魔掌，犹太人瓦尔特一家来到肯尼亚一个偏远的农场，刚开始，妻子耶特尔很不适应那里落后的生活，时时刻刻想返回故国；瓦尔特虽已对德国死心，但仍念念不忘..."},
{"name": "一个陌生女人的来信", "url": "https://book.douban.com/subject/6813214/", "comment_num": 191, "sub_tag_name": "茨威格", "tag_name": "文学", "score": 8.2, "book_id": "6813214", "description": "《电影中的记忆:一个陌生女人的来信》由斯蒂芬•茨威格编著。一个男子在41岁生日当天收到一封没有署名和地址的信，这封信出自一个临死的女人，讲述了一相刻骨铭心的..."},
{"name": "永久记忆版世界文学名著文库", "url": "https://book.douban.com/subject/1011359/", "comment_num": 15, "sub_tag_name": "茨威格", "tag_name": "文学", "score": 7.8, "book_id": "1011359", "description": "本书是从丰富多彩的世界文学之林精选出的不同代表性的传世名篇。作品启迪着我们的心智，呵护着我们的心灵，陶冶着我们的情操。对广大读者的人生观、价值观以及人格、修..."},
{"name": "一位陌生女子的來信", "url": "https://book.douban.com/subject/1361377/", "comment_num": 10, "sub_tag_name": "茨威格", "tag_name": "文学", "score": 0.0, "book_id": "1361377", "description": null},
{"name": "levoyagedanslepassé", "url": "https://book.douban.com/subject/3610632/", "comment_num": 10, "sub_tag_name": "茨威格", "tag_name": "文学", "score": 0.0, "book_id": "3610632", "description": "Levoyagedanslepasséestl'histoiredesretrouvaillesaugoûtamerentreun..."},
{"name": "莱茵河畔的森林之歌", "url": "https://book.douban.com/subject/1003092/", "comment_num": 32, "sub_tag_name": "茨威格", "tag_name": "文学", "score": 6.9, "book_id": "1003092", "description": "这套读物的特点：一、创新！我们的“人文素养读本”不单单是内容的堆砌，而是一条主线下的体系创新。由此及彼，由内及外，让我们在阅读中逐渐体会到人文的精神，获取..."},
{"name": "麦哲伦", "url": "https://book.douban.com/subject/1425185/", "comment_num": 17, "sub_tag_name": "茨威格", "tag_name": "文学", "score": 8.4, "book_id": "1425185", "description": "《布老虎传记文库•巨人百传丛书•英雄探险家卷•麦哲伦》主要内容：麦哲伦（Magellan，Ferdinand），葡萄牙著名航海家和探险家，先后为葡萄牙（15..."},
{"name": "三作家", "url": "https://book.douban.com/subject/22685326/", "comment_num": 27, "sub_tag_name": "茨威格", "tag_name": "文学", "score": 8.8, "book_id": "22685326", "description": "本书系我社“茨威格经典传纪丛书”之一种,分别为世界文坛上三个卓越的作家:意大利杰出作家卡萨诺瓦、法国作家司汤达和俄国批判现实主义作家列夫.托尔斯泰立传,展现..."},
{"name": "看不见的收藏(德汉对照分级读物)", "url": "https://book.douban.com/subject/1242263/", "comment_num": 92, "sub_tag_name": "茨威格", "tag_name": "文学", "score": 8.7, "book_id": "1242263", "description": "本书收录了奥地利著名作家茨威格的三篇中篇小说，从中我们可以感受到他那细致入微的心理刻画，以及对人物性格的精彩分析。《日内瓦湖的故事》描述了一个从法国战俘营..."},
{"name": "昨日世界：一個歐洲人的回憶", "url": "https://book.douban.com/subject/1763023/", "comment_num": 59, "sub_tag_name": "茨威格", "tag_name": "文学", "score": 8.5, "book_id": "1763023", "description": "「出於絕望，我正在寫我一生的歷史。」茨威格在致友人的書信中這麼說。這時茨威格正在寫他生命中的最後一本著作「昨日世界」，這部書也是茨威格的自傳，然而，「昨日世..."},
{"name": "一个陌生女人的来信", "url": "https://book.douban.com/subject/3201701/", "comment_num": 87, "sub_tag_name": "茨威格", "tag_name": "文学", "score": 8.8, "book_id": "3201701", "description": null},
{"name": "一个陌生女人的来信", "url": "https://book.douban.com/subject/10760907/", "comment_num": 86, "sub_tag_name": "茨威格", "tag_name": "文学", "score": 9.0, "book_id": "10760907", "description": null},
{"name": "人类的群星闪耀时", "url": "https://book.douban.com/subject/6864100/", "comment_num": 46, "sub_tag_name": "茨威格", "tag_name": "文学", "score": 8.5, "book_id": "6864100", "description": null},
{"name": "三大师传", "url": "https://book.douban.com/subject/26440785/", "comment_num": 73, "sub_tag_name": "茨威格", "tag_name": "文学", "score": 8.6, "book_id": "26440785", "description": "本书由19世纪三位杰出的文学大师巴尔扎克、狄更斯和陀思妥耶夫斯基的传论组成。巴尔扎克生当拿破仑崛起的时代，尽管他并未投身这支东征西讨的大军，然而拿破仑横绝一..."},
{"name": "同情的罪", "url": "https://book.douban.com/subject/1996564/", "comment_num": 54, "sub_tag_name": "茨威格", "tag_name": "文学", "score": 8.6, "book_id": "1996564", "description": "本书是茨威格在一九三八年流亡国外时发表的长篇小说，也是他生前面世的唯一的一部长篇小说。相比他的中短篇《同情的罪》的情节并不复杂：少尉霍夫米勒偶然认识贵族..."},
{"name": "昨日的世界", "url": "https://book.douban.com/subject/25906499/", "comment_num": 171, "sub_tag_name": "茨威格", "tag_name": "文学", "score": 9.0, "book_id": "25906499", "description": "一部让人真实了解第一次世界大战和第二次世界大战的书，一部让人在平静中感受震撼的书。奥地利著名作家斯蒂芬?茨威格的自传体回忆录，回忆了第一次世界大战前欧洲秩..."},
{"name": "一个陌生女人的来信", "url": "https://book.douban.com/subject/2379276/", "comment_num": 182, "sub_tag_name": "茨威格", "tag_name": "文学", "score": 8.7, "book_id": "2379276", "description": "在这部茨威格烩炙人口的心理分析小说集中，一段段哀婉动人的故事、在作者笔下娓娓道来，一个个人物的喜乐、苦痛、迷惘和绝望都能悄悄渗入你的心灵，触动那最深处的一隅..."},
{"name": "一个陌生女人的来信", "url": "https://book.douban.com/subject/26256868/", "comment_num": 137, "sub_tag_name": "茨威格", "tag_name": "文学", "score": 9.0, "book_id": "26256868", "description": "《一个陌生女人的来信：茨威格小说菁华集》是奥地利著名作家茨威格的代表作之一。其中最有名的是《一个陌生女人的来信》，讲述一个陌生的女人，在她生命的最后时刻写给..."},
{"name": "一个陌生女人的来信", "url": "https://book.douban.com/subject/25895962/", "comment_num": 71, "sub_tag_name": "茨威格", "tag_name": "文学", "score": 9.0, "book_id": "25895962", "description": "本书为茨威格中篇小说集，《一个陌生女人的来信》讲述一位男子在四十一岁生日当天收到一封厚厚的没有署名的信，信出自一位临终女子之手，字里行间是她对他十八年刻骨铭..."},
{"name": "茨威格作品精选", "url": "https://book.douban.com/subject/3100746/", "comment_num": 72, "sub_tag_name": "茨威格", "tag_name": "文学", "score": 9.2, "book_id": "3100746", "description": "《茨威格作品精选(插图本)》是茨威格作品精选集，书中具体收录了：《灼人的秘密》、《猩红热》、《一个陌生女人的来信》、《热带癫狂症患者》、《象棋的故事》、《拜..."},
{"name": "三大师", "url": "https://book.douban.com/subject/1736601/", "comment_num": 41, "sub_tag_name": "茨威格", "tag_name": "文学", "score": 8.4, "book_id": "1736601", "description": "《三大师》内容简介：在《三大师》中，茨威格把巴尔扎克，狄更斯和陀思妥耶夫斯基看做是叙事文学的天才，是百科全书式的作家。他在论述他们时，不是泛泛而谈，面面俱到..."},
{"name": "一个陌生女人的来信", "url": "https://book.douban.com/subject/6535064/", "comment_num": 108, "sub_tag_name": "茨威格", "tag_name": "文学", "score": 8.5, "book_id": "6535064", "description": "《世界文学名著典藏:一个陌生女人的来信(全译插图本)》讲述了：一个陌生的女人，在她生命的最后时刻，饱蘸着一生的痴情，写下了一封凄婉动人的长信，向一位著名的作..."},
{"name": "国际象棋的故事", "url": "https://book.douban.com/subject/1024060/", "comment_num": 159, "sub_tag_name": "茨威格", "tag_name": "文学", "score": 9.0, "book_id": "1024060", "description": "《国际象棋的故事》是茨威格生前发表的最后一部中篇小说。小说表面上讲述了一条从纽约开往南美的轮般上一位业余国际象象手击败了国际象棋世界冠军的故事，实际上近诉了..."},
{"name": "三大师", "url": "https://book.douban.com/subject/2101439/", "comment_num": 24, "sub_tag_name": "茨威格", "tag_name": "文学", "score": 8.8, "book_id": "2101439", "description": "《三大师》内容简介：在《三大师》中，茨威格把巴尔扎克，狄更斯和陀思妥耶夫斯基看做是叙事文学的天才，是百科全书式的作家。他在论述他们时，不是泛泛而谈，面面俱到..."},
{"name": "里昂的婚礼", "url": "https://book.douban.com/subject/3806575/", "comment_num": 99, "sub_tag_name": "茨威格", "tag_name": "文学", "score": 8.9, "book_id": "3806575", "description": "收入茨威格的《里昂的婚礼》、《象棋的故事》、《看不见的珍藏》和《一个陌生女人的来信》4篇力作。"},
{"name": "一颗心的沦亡", "url": "https://book.douban.com/subject/26118434/", "comment_num": 43, "sub_tag_name": "茨威格", "tag_name": "文学", "score": 9.1, "book_id": "26118434", "description": "《一颗心的沦亡》茨威格的作品擅长细致的性格刻画，以及对奇特命运下个人遭遇和心灵的描摹，尤其善于在激情的煎熬中洞察女性内心活动。本书收录二十余篇短篇名作，如《..."},
{"name": "精神疗法", "url": "https://book.douban.com/subject/2341937/", "comment_num": 41, "sub_tag_name": "茨威格", "tag_name": "文学", "score": 8.6, "book_id": "2341937", "description": "本书作者是以思想性见长的著名文学家、人物传记作家茨威格，他以优美的笔触，深刻独到的分析，论述发明催眠术的奥地利医生梅斯梅尔,基督教科学创始人玛丽.贝克尔-埃..."},
{"name": "邂逅人与书籍", "url": "https://book.douban.com/subject/25857441/", "comment_num": 37, "sub_tag_name": "茨威格", "tag_name": "文学", "score": 8.4, "book_id": "25857441", "description": "《邂逅人与书籍：茨威格读书随笔》是茨威格的文学评论集，包括作家介绍、作品评论、讲演、纪念文章、序言等不同体裁，论及世界文学史上许多伟大的作家，如卢梭、巴尔扎..."},
{"name": "良心反对暴力", "url": "https://book.douban.com/subject/1921079/", "comment_num": 34, "sub_tag_name": "茨威格", "tag_name": "文学", "score": 8.9, "book_id": "1921079", "description": null},
{"name": "三人书简", "url": "https://book.douban.com/subject/1898593/", "comment_num": 28, "sub_tag_name": "茨威格", "tag_name": "文学", "score": 8.5, "book_id": "1898593", "description": "本书收集了苏联作家髙尔基和法国作家罗曼•罗兰、奥地利作家茨威格的部分往来书信、电文，是一部外国书信体文学的范本。由于三位作家在往来书简中多次谈及了以下四篇佳..."},
{"name": "一个女人的24小时", "url": "https://book.douban.com/subject/1388331/", "comment_num": 67, "sub_tag_name": "茨威格", "tag_name": "文学", "score": 8.6, "book_id": "1388331", "description": null},
{"name": "巴尔扎克传", "url": "https://book.douban.com/subject/25882970/", "comment_num": 24, "sub_tag_name": "茨威格", "tag_name": "文学", "score": 8.9, "book_id": "25882970", "description": "《巴尔扎克传》是斯·茨威格的传记力作，他以小说家的笔法记录了文坛巨匠巴尔扎克的传奇一生。一方面让我们看到一个籍籍无名的外省文学青年如何奋斗不止，成为执法兰西..."},
{"name": "罗曼·罗兰传", "url": "https://book.douban.com/subject/1208897/", "comment_num": 32, "sub_tag_name": "茨威格", "tag_name": "文学", "score": 7.6, "book_id": "1208897", "description": "《斯台芬•茨威格集:罗曼•罗兰传》是茨威格传记系列中的一册，讲述了著名作家罗曼·罗兰的一生，表明了他一种不屈不挠的伟大精神和独具特色的人格魅力。茨威格的传记..."},
{"name": "麦哲伦传", "url": "https://book.douban.com/subject/1191019/", "comment_num": 24, "sub_tag_name": "茨威格", "tag_name": "文学", "score": 8.3, "book_id": "1191019", "description": "书本之所以产生，是由于有各种各样的情感需要表达。推动人们写书的，可以是一种灵感，也可以是一种谢忱；麦哲伦，著名航海家和探险家，第一个把环球航行理想付诸冒险运..."},
{"name": "象棋的故事", "url": "https://book.douban.com/subject/1210503/", "comment_num": 81, "sub_tag_name": "茨威格", "tag_name": "文学", "score": 9.3, "book_id": "1210503", "description": ""},
{"name": "一个陌生女人的来信", "url": "https://book.douban.com/subject/4880389/", "comment_num": 77, "sub_tag_name": "茨威格", "tag_name": "文学", "score": 9.0, "book_id": "4880389", "description": "《一个陌生女人的来信:茨威格小说精选》共收入其经典作品十篇，包括有被遗忘的梦、生命的奇迹、灼人的秘密、一个陌生女人的来信、一颗心的沦亡等。茨威格是弗洛伊德的..."},
{"name": "一个陌生女人的来信", "url": "https://book.douban.com/subject/4051532/", "comment_num": 81, "sub_tag_name": "茨威格", "tag_name": "文学", "score": 8.2, "book_id": "4051532", "description": "《一个陌生女人的来信》讲述的是一个陌生的女人，在她生命的最后时刻，饱蘸着一生的痴情，写下了一封凄婉动人的长信，向一位著名的作家袒露了自己绝望的爱慕之情。故事..."},
{"name": "心灵的焦灼", "url": "https://book.douban.com/subject/4743480/", "comment_num": 22, "sub_tag_name": "茨威格", "tag_name": "文学", "score": 9.4, "book_id": "4743480", "description": "同情恰好有两种。一种同情怯懦感伤，实际上只是心灵的焦灼。看到别人的不幸，急于尽快地脱身出来，以免受到感动，陷入难堪的境地。这种同情根本不是对别人的痛苦抱有同..."},
{"name": "一个陌生女人的来信", "url": "https://book.douban.com/subject/5338526/", "comment_num": 72, "sub_tag_name": "茨威格", "tag_name": "文学", "score": 8.9, "book_id": "5338526", "description": "《一个陌生女人的来信(插图本)》内容简介：茨威格是享有世界声誉的奥地利作家，他善于从心理角度再现人物的性格和生活遭遇，特别擅长塑造女性形象，刻画女性心理。把..."},
{"name": "茨威格传记精华――罗曼・罗兰", "url": "https://book.douban.com/subject/1016247/", "comment_num": 22, "sub_tag_name": "茨威格", "tag_name": "文学", "score": 8.3, "book_id": "1016247", "description": "奥地利大作家斯苔芬・茨威格（1881－1942）擅长写传记作品，有《三大师》、《三诗人》等精典之作传世。他与罗曼・罗兰熟识，且私交甚笃，本书是他满怀深情之作..."},
{"name": "心灵的焦躁", "url": "https://book.douban.com/subject/1192728/", "comment_num": 37, "sub_tag_name": "茨威格", "tag_name": "文学", "score": 8.5, "book_id": "1192728", "description": "《心灵的焦躁/世界文学名著宝库》内容为：世界文学名著以其优美的文字、丰富的艺术表现及所展现的广阔的社会现实和深刻的思想内涵，长期以来一直为广大读者所喜爱。世..."},
{"name": "罗曼·罗兰", "url": "https://book.douban.com/subject/1642814/", "comment_num": 15, "sub_tag_name": "茨威格", "tag_name": "文学", "score": 7.9, "book_id": "1642814", "description": ""},
{"name": "人类群星闪耀时（全本）", "url": "https://book.douban.com/subject/27124581/", "comment_num": 26, "sub_tag_name": "茨威格", "tag_name": "文学", "score": 8.9, "book_id": "27124581", "description": "《人类群星闪耀时(译美文)》由茨威格所著，拜占庭的沦陷、亨德尔的重生、一个流星般的天才、玛丽恩巴德的挽歌……这10个历史瞬间神奇般地降临到10位人物的身上，..."},
{"name": "海滨之屋", "url": "https://book.douban.com/subject/1208899/", "comment_num": 40, "sub_tag_name": "茨威格", "tag_name": "文学", "score": 8.0, "book_id": "1208899", "description": "本书是奥地利著名作家斯台芬·茨威格的一部戏剧作品，讲述了十八世纪德国某港口城市的领港员哥特霍尔特·克吕格在家里开了一家酒店。就在这座“海滨之屋”里，演出了一..."},
{"name": "与魔搏斗的人", "url": "https://book.douban.com/subject/1642810/", "comment_num": 14, "sub_tag_name": "茨威格", "tag_name": "文学", "score": 8.2, "book_id": "1642810", "description": "在《与魔搏斗的人：荷尔德林、克莱斯特、尼采》这部作品里又像以前的三部曲《三大师》中一样描绘了三个文学大师的形象，他们因其内在的共同性相聚在一起。荷尔德林、克..."},
{"name": "茨威格小说研究", "url": "https://book.douban.com/subject/1548196/", "comment_num": 32, "sub_tag_name": "茨威格", "tag_name": "文学", "score": 6.1, "book_id": "1548196", "description": "《茨威格小说研究》对这位奥地利文学大师的犹太出身、文学创作历程等进行人物分析，并对其小说作品进行文本研究，且从大师的细节描写、心理刻画等方面论述其艺术特色。..."},
{"name": "为爱疯狂", "url": "https://book.douban.com/subject/1118817/", "comment_num": 44, "sub_tag_name": "茨威格", "tag_name": "文学", "score": 8.5, "book_id": "1118817", "description": null}]