[{"name": "出国自助游教室", "url": "https://book.douban.com/subject/10566257/", "comment_num": 1192, "sub_tag_name": "自助游", "tag_name": "生活", "score": 8.0, "book_id": "10566257", "description": "《出国自助游教室:我的第一本旅行教科书》不是一本单纯的游记，这是一本以游记的方式展现给大家的出国自助游“教科书”。如果你希望买一本如何计划欧洲、美洲或者东..."},
{"name": "老火车的时光慢游", "url": "https://book.douban.com/subject/10945439/", "comment_num": 558, "sub_tag_name": "自助游", "tag_name": "生活", "score": 7.5, "book_id": "10945439", "description": "本书是作者乘坐绿皮火车旅行的游记。作者走黔西之川，行彩云之南，踏天府之国，经三秦之地，过陇西之路，至青色之海，达东北之极，详细介绍了值得体验的３５段绿皮火车..."},
{"name": "意大利", "url": "https://book.douban.com/subject/2122173/", "comment_num": 269, "sub_tag_name": "自助游", "tag_name": "生活", "score": 8.7, "book_id": "2122173", "description": "使用LonelyPlanet旅行指南的最让人开心的，就是你可以选择任何自己喜欢的旅行方式。LonelyPlanet相信，旅行中最难忘的经历往往是那此出乎..."},
{"name": "青海全攻略", "url": "https://book.douban.com/subject/2261773/", "comment_num": 40, "sub_tag_name": "自助游", "tag_name": "生活", "score": 7.7, "book_id": "2261773", "description": "当人们厌倦了北京长城的人山人海，当人们厌倦了杭州西湖的小家碧玉，厌倦了安徽黄山的险峻怪异，厌倦了四川九寨沟的碧波不惊……一个多年来被人们忽视、遗忘的高原地带..."},
{"name": "100元狂走中国", "url": "https://book.douban.com/subject/1186894/", "comment_num": 229, "sub_tag_name": "自助游", "tag_name": "生活", "score": 7.6, "book_id": "1186894", "description": "《￥100元狂走中国》介绍：带着100元人民币，她开始走同周游中国各地的旅程。一个刚刚大学毕业的21岁女孩，凭借着自己对祖国山河的一腔热爱，历时一年多，游历..."},
{"name": "我把欧洲塞进背包", "url": "https://book.douban.com/subject/1187494/", "comment_num": 373, "sub_tag_name": "自助游", "tag_name": "生活", "score": 7.3, "book_id": "1187494", "description": "《我把欧洲塞进背包》使用了大量的图片，拍摄的时候，并不是从摄影师的角度，作者只是一个过客与一个记录的人。书中文章主要以一种短小精悍的小品文性格出现，一切以性..."},
{"name": "巴黎", "url": "https://book.douban.com/subject/3775827/", "comment_num": 84, "sub_tag_name": "自助游", "tag_name": "生活", "score": 8.7, "book_id": "3775827", "description": "“TimeOut”之《巴黎》以生动的笔触描绘了隽永的法国浪漫之都。撰文者给予那些或古老或新潮且经久不衰的事物以密切关注，另辟蹊径，规避俗套，热忱引领读者走..."},
{"name": "高原上", "url": "https://book.douban.com/subject/27001284/", "comment_num": 16, "sub_tag_name": "自助游", "tag_name": "生活", "score": 9.6, "book_id": "27001284", "description": "《高原上》一书是两位作者一家三人由澳大利亚出发，在南美洲旅行的游记，记录了他们在圣地亚哥、布宜诺斯艾利斯、利马等城市和秘鲁高原上旅行的所见所想，在这些游记中..."},
{"name": "越南自助游", "url": "https://book.douban.com/subject/1734107/", "comment_num": 99, "sub_tag_name": "自助游", "tag_name": "生活", "score": 7.3, "book_id": "1734107", "description": "小资艳情——胡志明市，度假胜地——大叻；浪漫海岛——芽庄；宁静古城——会安；——皇城根下——顺化；沧桑古都——河内……本书带你走进充满异域风情的越南。全书图..."},
{"name": "沙发旅行", "url": "https://book.douban.com/subject/4873796/", "comment_num": 737, "sub_tag_name": "自助游", "tag_name": "生活", "score": 7.6, "book_id": "4873796", "description": "让一个陌生人进入家里，分享你的食物、床单、浴室，甚至马桶……可以吗？本书作者亲历“沙发旅行”这种风靡国外的新生旅行方式。背上背包，走出国门，游历欧洲——法..."},
{"name": "中国自助游", "url": "https://book.douban.com/subject/25985823/", "comment_num": 37, "sub_tag_name": "自助游", "tag_name": "生活", "score": 7.7, "book_id": "25985823", "description": "外出旅行时最需要的是什么？是最便捷的交通路线资讯，最经济的出行线路安排，最真实有趣的游玩体验，《中国自助游》无疑是你的贴身小助手，满足你一切旅途需求。经典..."},
{"name": "伦敦", "url": "https://book.douban.com/subject/4898629/", "comment_num": 144, "sub_tag_name": "自助游", "tag_name": "生活", "score": 8.7, "book_id": "4898629", "description": "触动我们心弦的，或许是那个作绿树装扮、在科芬园圣保罗教堂脚下对镜定妆的街头艺人，又或许是那群拗着朋克造型、围坐在大本钟下构成如画般街景的孩子，无论如何，细览..."},
{"name": "台北旅遊全攻略", "url": "https://book.douban.com/subject/2081784/", "comment_num": 33, "sub_tag_name": "自助游", "tag_name": "生活", "score": 8.1, "book_id": "2081784", "description": "◆◆◆定期Followup．時刻與台北Catchup◆◆◆全書加厚至208頁．綜合台北好玩好食250處．新手、老饕必備！一本好的旅遊書不單切..."},
{"name": "雪山乌托邦", "url": "https://book.douban.com/subject/26266258/", "comment_num": 54, "sub_tag_name": "自助游", "tag_name": "生活", "score": 7.7, "book_id": "26266258", "description": "这不仅仅是一本游记，时间跨度超过六年。因为一处美景，换了一种活法，听起来不可思议。他们辞掉工作，走进大山深处，从云南到西藏，从虫草江湖到松茸传奇，住在高山营..."},
{"name": "青海/藏羚羊自助旅行手册", "url": "https://book.douban.com/subject/1427565/", "comment_num": 50, "sub_tag_name": "自助游", "tag_name": "生活", "score": 7.9, "book_id": "1427565", "description": "对所有的年青人而言，拓展生命空间，增长见识，学习对不同地域、不同民族、不同生存状态和价值观的关爱和欣赏都是我们成长过程中的真义所在。因此旅行就成为必..."},
{"name": "2011中国自助游全新彩色升级版", "url": "https://book.douban.com/subject/2102045/", "comment_num": 308, "sub_tag_name": "自助游", "tag_name": "生活", "score": 7.4, "book_id": "2102045", "description": "《中国自助游(2011全新彩色升级版畅销10周年纪念版)》10周岁了！10年来，在热心读者的支持下，我们始终保持着旅游类图书销售总冠军的荣誉。10周年纪念，..."},
{"name": "LonelyPlanet旅行指南系列：韩国（2013年全新版）", "url": "https://book.douban.com/subject/25766302/", "comment_num": 92, "sub_tag_name": "自助游", "tag_name": "生活", "score": 7.0, "book_id": "25766302", "description": "韩国是一个新与旧并存的迷人国度，古意绵绵的宫殿与时尚现代的都市气质相得益彰。这里是韩国服饰、美容、美食、韩剧爱好者的圣地。樱花飞舞的春天，去风光旖旎的济州..."},
{"name": "明天就去尼泊尔", "url": "https://book.douban.com/subject/1442469/", "comment_num": 180, "sub_tag_name": "自助游", "tag_name": "生活", "score": 7.1, "book_id": "1442469", "description": "本书主要讲述了加德满都、帕坦、巴德岗、藏传佛教在尼泊尔、皇家奇特旺国家森林公园、博卡拉等内容。"},
{"name": "中国古镇游", "url": "https://book.douban.com/subject/2381480/", "comment_num": 248, "sub_tag_name": "自助游", "tag_name": "生活", "score": 7.7, "book_id": "2381480", "description": "《中国古镇游》2008全新升级版，依据2008年法定假日调整方案，结合中国最新旅游趋势，全面升级古镇旅游攻略，让您体验一次真正的民俗趣味之旅。《中国古镇游..."},
{"name": "南美洲", "url": "https://book.douban.com/subject/2364643/", "comment_num": 88, "sub_tag_name": "自助游", "tag_name": "生活", "score": 8.6, "book_id": "2364643", "description": "挑战？没错。回报？超出你最狂野的梦想。南美洲就是为旅行——为那种你一生一世梦寐以求的摄人心魄、令人惊喜、激动人心的旅行——而造就的。在科迪勒拉山间跋涉，在亚..."},
{"name": "丽江的柔软时光", "url": "https://book.douban.com/subject/1068637/", "comment_num": 366, "sub_tag_name": "自助游", "tag_name": "生活", "score": 7.8, "book_id": "1068637", "description": "好玩的旅游书，随意的很“旅行本是一个极富诗意的行为，读来读去，只是告诉你怎走，是很乏味的，旅行怎可没有那温柔的心意？”1、这是一本关于关怀的书旅行类图..."},
{"name": "2013年中国自助游（全新升级第13版）", "url": "https://book.douban.com/subject/6808157/", "comment_num": 151, "sub_tag_name": "自助游", "tag_name": "生活", "score": 7.1, "book_id": "6808157", "description": "外出旅行时最需要的是什么？是最实用的交通路线资讯，最划算的出行线路安排，最真实给力的游玩体验，而《中国自助游》可以满足你一切旅途需求。经典畅销11年的《中..."},
{"name": "维也纳", "url": "https://book.douban.com/subject/3115690/", "comment_num": 33, "sub_tag_name": "自助游", "tag_name": "生活", "score": 8.6, "book_id": "3115690", "description": "《维也纳》内容简介：“TimeOut城市指南”丛书均由当地编者精心编写，视角独到。其内容不仅广泛涉及文化艺术领域，而且还收录了数百篇独立评论，以同飨读者。..."},
{"name": "旧金山", "url": "https://book.douban.com/subject/4605585/", "comment_num": 35, "sub_tag_name": "自助游", "tag_name": "生活", "score": 7.8, "book_id": "4605585", "description": "旧金山城市不大，名气可不小。这座方圆7平方英里的城市位于太平洋沿岸的一个半岛上，其无与伦比的都市和自然景观在全世界都赫赫有名。旧金山拥有起伏的山坡、有轨电..."},
{"name": "我去!拉萨", "url": "https://book.douban.com/subject/10807777/", "comment_num": 390, "sub_tag_name": "自助游", "tag_name": "生活", "score": 7.5, "book_id": "10807777", "description": "《我去!拉萨》内容简介：毕业季的7个非典型宅男，告别书房和网络，告别熬夜和赖床，骑上单车，直指拉萨！这里有，最尽兴的漂泊，最传奇的花甲骑士，最浪漫的路上爱情..."},
{"name": "从法棍到米粉的越南行", "url": "https://book.douban.com/subject/6977224/", "comment_num": 142, "sub_tag_name": "自助游", "tag_name": "生活", "score": 7.5, "book_id": "6977224", "description": "此书源自发表在天涯论坛旅游版的人气热帖《Same,same,Vietnam!从法棍到米粉——两个女生行走越南的15天（光影随行）》，网络点击量突破80万!..."},
{"name": "罗马", "url": "https://book.douban.com/subject/3245979/", "comment_num": 49, "sub_tag_name": "自助游", "tag_name": "生活", "score": 7.9, "book_id": "3245979", "description": "这一版的TimeOut之《罗马》是将目光放在罗马的过去，侧重介绍古罗马社会，去看待它的阶层、它的法规、它的伟大领袖和那些离经叛道的怪人。是什么促使我们重..."},
{"name": "欧洲经典游", "url": "https://book.douban.com/subject/1765968/", "comment_num": 67, "sub_tag_name": "自助游", "tag_name": "生活", "score": 8.0, "book_id": "1765968", "description": "精挑细选：欧洲12个国家、28个城市、500个景点的专业推介聚焦人文：对每个景点的文化背景和特色作精彩讲述，再配以新颖独到的小贴士兼顾实用：让你轻松..."},
{"name": "六感漂泊：尼泊尔零钱惊艳之旅", "url": "https://book.douban.com/subject/1431137/", "comment_num": 244, "sub_tag_name": "自助游", "tag_name": "生活", "score": 6.8, "book_id": "1431137", "description": "尼泊尔将震撼你的六感并使之升华。作为世界惟一以印度教为国教的国家和释迦牟尼的祖国，她至今保留着供奉活女神的传统，拥有七处世界遗产，并一度成为嬉皮士的第二故乡..."},
{"name": "侣行天下", "url": "https://book.douban.com/subject/2188843/", "comment_num": 118, "sub_tag_name": "自助游", "tag_name": "生活", "score": 7.2, "book_id": "2188843", "description": null},
{"name": "我将心丢在喜玛拉雅", "url": "https://book.douban.com/subject/3794340/", "comment_num": 40, "sub_tag_name": "自助游", "tag_name": "生活", "score": 7.2, "book_id": "3794340", "description": "《我将心丢在喜玛拉雅:从拉萨到加德满都》内容简介：这是一个年轻女孩的旅行手记，她在一个月里，转遍了西藏和尼泊尔最美的地方。生动优美的文字和图片让你有身临其境..."},
{"name": "嘻行中欧", "url": "https://book.douban.com/subject/22279227/", "comment_num": 10, "sub_tag_name": "自助游", "tag_name": "生活", "score": 0.0, "book_id": "22279227", "description": null},
{"name": "最美秦晋", "url": "https://book.douban.com/subject/6960423/", "comment_num": 11, "sub_tag_name": "自助游", "tag_name": "生活", "score": 8.5, "book_id": "6960423", "description": "现代社会越来越追求有个性有特色的旅行，淡化走马观花的传统方式，追求历史文化民俗的深度感悟、风景美食住宿的独特体验。《最美旅游线路丛书》在这方面开创了先河..."},
{"name": "两个人的爱琴海", "url": "https://book.douban.com/subject/1470213/", "comment_num": 219, "sub_tag_name": "自助游", "tag_name": "生活", "score": 7.7, "book_id": "1470213", "description": "图书目录我能想到的最浪漫的事追赶云端的阿波罗曙光(9月15日～16日)爱琴海，当我们四目相对(9月17日)美人鱼带领小鱼巡游(9月18日～19日)..."},
{"name": "老挝、泰国自驾游", "url": "https://book.douban.com/subject/4709261/", "comment_num": 27, "sub_tag_name": "自助游", "tag_name": "生活", "score": 8.7, "book_id": "4709261", "description": "《老挝泰国自驾游》主要内容简介：以每天为章节记录，以图片和文字的形式呈现。从出发前的各项准备，老挝、泰国的签证手续及车辆的手续办理的详细过程，到自驾途中遇到..."},
{"name": "大学生旅游圣经", "url": "https://book.douban.com/subject/1897679/", "comment_num": 45, "sub_tag_name": "自助游", "tag_name": "生活", "score": 7.0, "book_id": "1897679", "description": "精心设计了八条适合大学生旅游的经典路线，关注大学生优惠门票，以最经济的住宿、餐饮、交通来为你的旅途制定合适的预算，并以高校最为集中的北京、上海、西安、武汉、..."},
{"name": "情迷首尔之旅", "url": "https://book.douban.com/subject/6313274/", "comment_num": 70, "sub_tag_name": "自助游", "tag_name": "生活", "score": 6.7, "book_id": "6313274", "description": "想去旅行，不要跟团。想独辟蹊径，不要走大众线路。想随性地走走停停，不要观光购物一条龙。这个春天，就带着“小国风情游”上路吧！就去迷人的小国——去看奇..."},
{"name": "在全世界的边缘呼唤爱", "url": "https://book.douban.com/subject/25849536/", "comment_num": 69, "sub_tag_name": "自助游", "tag_name": "生活", "score": 7.0, "book_id": "25849536", "description": "本书讲述作者因为爱情、家庭等变故，做了一个奇怪的梦，梦里的场景美轮美奂，醒来后，她决定去找寻梦中的地方，借以疗伤。她走遍欧洲，最后来到非洲，终于找到了自己梦..."},
{"name": "LonelyPlanetTaiwan(LonelyPlanetTaiwan)", "url": "https://book.douban.com/subject/1379927/", "comment_num": 19, "sub_tag_name": "自助游", "tag_name": "生活", "score": 7.8, "book_id": "1379927", "description": "IlhaFormosa,the'beautifulisle',isamodernsocietysteepedinChineseher..."},
{"name": "东京购物终极指南", "url": "https://book.douban.com/subject/25897415/", "comment_num": 13, "sub_tag_name": "自助游", "tag_name": "生活", "score": 7.9, "book_id": "25897415", "description": "★东京超级血拼指南书，实用100%★逾3000张图解，超500个东京热门购物胜地特色商品店面，详细列出营业时间、交通位置、品牌特色、网址等相关资讯..."},
{"name": "中国古镇游", "url": "https://book.douban.com/subject/1957182/", "comment_num": 63, "sub_tag_name": "自助游", "tag_name": "生活", "score": 6.8, "book_id": "1957182", "description": "《中国古镇游(第6版2007全新升级)》内容简介："},
{"name": "2007全新升级中国自助游", "url": "https://book.douban.com/subject/1945763/", "comment_num": 183, "sub_tag_name": "自助游", "tag_name": "生活", "score": 7.7, "book_id": "1945763", "description": "本书介绍149个旅游城市和景区、1766个景点，120条经典线路，500条独具特色的个性线路。"},
{"name": "中国自助游", "url": "https://book.douban.com/subject/1062105/", "comment_num": 67, "sub_tag_name": "自助游", "tag_name": "生活", "score": 7.7, "book_id": "1062105", "description": "本书主要不再提供景点介绍之类大而无用的内容，而是致力于告诉每位正准备抛开旅行社的旅游者：你出行前应如何做好最充分的准备工作；本书不在乎景点名气大小或旅游的开..."},
{"name": "尼泊尔", "url": "https://book.douban.com/subject/2148827/", "comment_num": 89, "sub_tag_name": "自助游", "tag_name": "生活", "score": 7.7, "book_id": "2148827", "description": "《尼泊尔》中的文字与图片均系作者亲自踩线所得，书中推荐的线路与玩法也系作者亲身体验提炼而成，作者以独有的女性视角和经济旅行态度讲述了发生在旅途中的乐事、趣事..."},
{"name": "印度——走遍全球", "url": "https://book.douban.com/subject/1843227/", "comment_num": 87, "sub_tag_name": "自助游", "tag_name": "生活", "score": 7.3, "book_id": "1843227", "description": "《印度》是《走遍全球》系列丛书之一。《印度》四色彩印，装帧精美，资料详实，内容实用，既是一本立刻就能用到的实践中的旅游指南，也具有可以使人们了解印度的入门书..."},
{"name": "土耳其和伊斯坦布尔", "url": "https://book.douban.com/subject/4916062/", "comment_num": 81, "sub_tag_name": "自助游", "tag_name": "生活", "score": 8.0, "book_id": "4916062", "description": "《土耳其和伊斯坦布尔》主要内容简介：《走遍全球》是一套为中国公民出国（境）旅游提供帮助的指南类系列丛书。从1998年至今，已出版了40余本,基本涵盖了中国公..."},
{"name": "西藏", "url": "https://book.douban.com/subject/1082413/", "comment_num": 83, "sub_tag_name": "自助游", "tag_name": "生活", "score": 7.7, "book_id": "1082413", "description": null},
{"name": "行走在欧罗巴的苍穹下", "url": "https://book.douban.com/subject/3572839/", "comment_num": 87, "sub_tag_name": "自助游", "tag_name": "生活", "score": 7.0, "book_id": "3572839", "description": "《行走在欧罗巴的苍穹下》是作者在欧洲生活和旅行的经历和体验。作者以多元化的工作与生活经历，以独特的文化与历史视角，让我们看到了伦敦的真实与经典、梵蒂冈的神灵..."},
{"name": "中国最美的88个自然风光旅游地", "url": "https://book.douban.com/subject/5997829/", "comment_num": 17, "sub_tag_name": "自助游", "tag_name": "生活", "score": 7.1, "book_id": "5997829", "description": "《中国最美的88个自然风光旅游地》内容系作者原创，是他们心灵的真实感悟；照片系作者亲自拍摄，是他们对美的瞬间永恒的诠释。饱含人文底蕴的文字配上震撼人心的精美..."},
{"name": "带着家走天涯", "url": "https://book.douban.com/subject/24294509/", "comment_num": 10, "sub_tag_name": "自助游", "tag_name": "生活", "score": 0.0, "book_id": "24294509", "description": "作者驾龄不满五年，退休之后开着一辆二手国产房车，两年间行遍欧亚大陆，行程6万多公里，被誉为“国产房车旅行第一人”。本书是他房车旅行经历的记录和提炼：从东南..."},
{"name": "完全自游京都·奈良", "url": "https://book.douban.com/subject/5405150/", "comment_num": 41, "sub_tag_name": "自助游", "tag_name": "生活", "score": 7.8, "book_id": "5405150", "description": "《完全自游京都·奈良》简介：Mook多次往返京都奈良，今年我们再度拜访古都，带回来进一步的旅游信息。《完全自游京都·奈良》由京都·奈良十件要做的事作为起始，..."},
{"name": "悉尼", "url": "https://book.douban.com/subject/3286054/", "comment_num": 36, "sub_tag_name": "自助游", "tag_name": "生活", "score": 8.0, "book_id": "3286054", "description": "2008年1月，作为澳大利亚节的一项内容，新南威尔士州州长莫里斯·勒马（MorrisLemma）正式任命女子冲浪冠军莱恩·比齐利（LayneBeachl..."},
{"name": "云南天堂", "url": "https://book.douban.com/subject/1703959/", "comment_num": 131, "sub_tag_name": "自助游", "tag_name": "生活", "score": 8.0, "book_id": "1703959", "description": "《云南天堂:自游主义者的暴走圣经》是一本富有文化含量的实用自助旅行指南。它十分注重对自助旅行者的人文关怀、情感关怀和资讯关怀。它提供给背包族的，是一个涵盖了..."},
{"name": "江苏上海古镇书", "url": "https://book.douban.com/subject/1217511/", "comment_num": 23, "sub_tag_name": "自助游", "tag_name": "生活", "score": 6.8, "book_id": "1217511", "description": "全面精选二十五座古镇，代表了江苏、上海境内古镇的不同风格，堪称经典；真实所收录的古镇全部经过紫图《古镇书编辑部》特派记者亲历实地的采访和拍摄，来自当地的第一..."},
{"name": "90元走中国", "url": "https://book.douban.com/subject/21241289/", "comment_num": 20, "sub_tag_name": "自助游", "tag_name": "生活", "score": 7.2, "book_id": "21241289", "description": "《90元走中国》内容简介：一位普普通通的90后男孩儿，一个走遍中国的简单梦想，一段出发时仅有90元的无悔旅程，三者融合在一起，就是你手中的这本《90元走中国..."},
{"name": "人生必去的101个地方", "url": "https://book.douban.com/subject/10466005/", "comment_num": 10, "sub_tag_name": "自助游", "tag_name": "生活", "score": 7.7, "book_id": "10466005", "description": "《世界印象•人生必去的101个地方(外国篇)》内容简介：综合多家专业旅游网站的景点排名，介绍最受欢迎的旅游热点。每一篇文章和每一幅图片，都能带给读者身临其境..."},
{"name": "徒步·加德满都到拉萨", "url": "https://book.douban.com/subject/1765965/", "comment_num": 49, "sub_tag_name": "自助游", "tag_name": "生活", "score": 7.0, "book_id": "1765965", "description": "《徒步•加德满都到拉萨》是作者由中尼公路进藏，徒步进行文化探险考察活动的散记。作者用46天时间，走过中尼公路全程1099公里，沿途穿越喜马拉雅山和农牧区。《..."},
{"name": "越南", "url": "https://book.douban.com/subject/3058854/", "comment_num": 116, "sub_tag_name": "自助游", "tag_name": "生活", "score": 6.8, "book_id": "3058854", "description": "《越南》是俭游天下丛书之一，其是根据中国读者的阅读和行走方式而特制的旅游指南。以中国背包客的视角全方位详细介绍越南旅游资源，用实践经验总结并推荐一条足以代表..."},
{"name": "德意志印象", "url": "https://book.douban.com/subject/1223779/", "comment_num": 104, "sub_tag_name": "自助游", "tag_name": "生活", "score": 7.9, "book_id": "1223779", "description": "作者只会开自动档车，却喜欢驾车远行，只会简单英语，却喜欢出国旅行，只写过几篇游记，从没想过拥有一本自己的书。其实旅行只需要一点勇气加一本好书！作为第一个..."},
{"name": "马来西亚自助游", "url": "https://book.douban.com/subject/1485666/", "comment_num": 18, "sub_tag_name": "自助游", "tag_name": "生活", "score": 5.7, "book_id": "1485666", "description": "多元文化别样风情、自助游的天堂、集合亚洲魅力、每一个人的乐土、热带的伊甸园、热带岛屿、众多世界之最、亚洲保存最好的秘密、冒险家乐园、美食王国饕餮之旅，是你爱..."},
{"name": "2010中国自助游", "url": "https://book.douban.com/subject/4177143/", "comment_num": 67, "sub_tag_name": "自助游", "tag_name": "生活", "score": 8.2, "book_id": "4177143", "description": "资历最老，修订最长：作为我国自助游类图书的开山鼻祖，《中国自助游》2010年己出版第11版，这是国内图书市场唯一的一本连续11年升级的旅行手册。11年的景点..."},
{"name": "中国最美的88个特色旅游地", "url": "https://book.douban.com/subject/6101663/", "comment_num": 28, "sub_tag_name": "自助游", "tag_name": "生活", "score": 7.6, "book_id": "6101663", "description": "“最美中国系列”丛书是旅游圣经团队历经数年发展、走遍中国后推出的巅峰之作。团队组织所有优秀作者撰写本系列，可谓十余位资深背包客视野中的“最美中国”。本系列丛..."},
{"name": "海外一周自助游", "url": "https://book.douban.com/subject/20477044/", "comment_num": 23, "sub_tag_name": "自助游", "tag_name": "生活", "score": 8.3, "book_id": "20477044", "description": null},
{"name": "你，就是冒险王", "url": "https://book.douban.com/subject/4127115/", "comment_num": 28, "sub_tag_name": "自助游", "tag_name": "生活", "score": 7.9, "book_id": "4127115", "description": "放膽擁抱自己的夢想，我就是冒險王！2006年，我揹起22.5公斤的巨大背包，去澳洲打工旅行！從布里斯本出發，帶著微薄旅費，像個流浪漢東西南北跑。只要有..."},
{"name": "追寻梦里的中土乐园", "url": "https://book.douban.com/subject/2250135/", "comment_num": 102, "sub_tag_name": "自助游", "tag_name": "生活", "score": 7.6, "book_id": "2250135", "description": "《魔戒》（《指环王》）里美丽的让人窒息的风景全部来自于新西兰。Hawky和Sissi被《魔戒》里的中土风景所引诱，于是踏上了追寻梦里中土乐园的旅途。十九天的..."},
{"name": "开始在新加坡自助旅行", "url": "https://book.douban.com/subject/3145641/", "comment_num": 40, "sub_tag_name": "自助游", "tag_name": "生活", "score": 7.0, "book_id": "3145641", "description": "内容简介新加坡不再只属于商务客了。如雨后春笋般落成的购物中心，夜店，时髦个性商店，展现多种族特点的异国美食……多样的活动类型，密集的街道分区规划，早就是想趁..."},
{"name": "一路东去", "url": "https://book.douban.com/subject/21339181/", "comment_num": 50, "sub_tag_name": "自助游", "tag_name": "生活", "score": 7.2, "book_id": "21339181", "description": "《一路东去:我用微博游中国》中108天的行走，绝不仅仅只是一次旅游。在这些日子里，路东遇到了各种各样的人，经历了各种各样的事。一路上，路东接受着来自五湖四海..."},
{"name": "台湾自助游", "url": "https://book.douban.com/subject/5960118/", "comment_num": 15, "sub_tag_name": "自助游", "tag_name": "生活", "score": 7.0, "book_id": "5960118", "description": "《自助旅行地图完全手册:台湾自助游》所列各景点均标明详细地址、电话、交通指南，编辑部尽最大努力保持资料的准确性，但由于各地旅游景点的交通、住宿、价格等讯息随..."},
{"name": "旅行的智慧", "url": "https://book.douban.com/subject/10747491/", "comment_num": 11, "sub_tag_name": "自助游", "tag_name": "生活", "score": 7.4, "book_id": "10747491", "description": "《旅行的智慧:来自美国外事培训专家的海外出行安全手册》献给每一位拥有护照的人！当全球各国紧密连接，跨国旅游、公务已经随处可见的今天，我们需要掌握足够的知识来..."},
{"name": "杭州玩全攻略", "url": "https://book.douban.com/subject/4862639/", "comment_num": 23, "sub_tag_name": "自助游", "tag_name": "生活", "score": 7.3, "book_id": "4862639", "description": "《杭州玩全攻略(2013-2014全彩版)》内容简介：玩家必备酷游秘籍！耀荐杭州热地大赏！最热门地抢鲜看!涵盖西湖、断桥、苏堤、白堤、岳王庙、孤山、西泠印社..."},
{"name": "乌镇的似水年华", "url": "https://book.douban.com/subject/1154227/", "comment_num": 58, "sub_tag_name": "自助游", "tag_name": "生活", "score": 7.4, "book_id": "1154227", "description": "乌镇，在我们的心目中，是一个诗意的梦境之地，需要一颗颗温柔的心意来观照，来感悟。所以，这本书没有地图，没有旅游指南，没有景点描述，也没有背景交代，甚至每一..."},
{"name": "驴友圣经", "url": "https://book.douban.com/subject/3405790/", "comment_num": 15, "sub_tag_name": "自助游", "tag_name": "生活", "score": 7.1, "book_id": "3405790", "description": "在远天的底下，有着无穷的诱惑。从“中国最美丽的乡村”婺源到“人类疲惫心灵最后的家园”黔东南；从“佛祖留在尘世的最后一个天堂”甘南，到“一部关于自然、历史和人..."},
{"name": "八条顶级线路玩转西部", "url": "https://book.douban.com/subject/3825088/", "comment_num": 34, "sub_tag_name": "自助游", "tag_name": "生活", "score": 7.7, "book_id": "3825088", "description": "《八条顶级线路·玩转西部》讲述了：一年中，会有大半年的时间穿行在中国西部那片神秘的高原之中。很多地方熟悉的如同自己生活的这个城市，然而，每次到了这些地方，却..."},
{"name": "2009年中国自助游（全新升级）", "url": "https://book.douban.com/subject/2359268/", "comment_num": 340, "sub_tag_name": "自助游", "tag_name": "生活", "score": 7.5, "book_id": "2359268", "description": "无论你是第一次旅行，或者是已经独自漫游过很多次，甚至是一个熟门熟路的资深玩家，《中国自助游》2008年升级版将带给你一样的惊喜！作为连续8年中国最畅销的自..."},
{"name": "LonelyPlanet孤独星球:东北（2014年版）", "url": "https://book.douban.com/subject/26247176/", "comment_num": 69, "sub_tag_name": "自助游", "tag_name": "生活", "score": 7.5, "book_id": "26247176", "description": "从北极村到旅顺口，从零下30℃到零上30℃，这片历经沧桑的黑土地在一次次冰雪消融后重焕生机。这里有冰天雪地里的热情奔放，可以满足你对冰雪与寒冷的所有想象；有..."},
{"name": "印度七城行记", "url": "https://book.douban.com/subject/25854543/", "comment_num": 28, "sub_tag_name": "自助游", "tag_name": "生活", "score": 8.5, "book_id": "25854543", "description": "一本图文并茂，游记和攻略相结合的背包客印度游记，火葬、童婚、恒河夜祭、印度庙祭祀，从繁华的孟买到水乡环绕的南印度，七座风光旖旎的古城。作者流连秘密花园，在恒..."},
{"name": "畅游日本－悠生活.旅游大玩家", "url": "https://book.douban.com/subject/6802547/", "comment_num": 25, "sub_tag_name": "自助游", "tag_name": "生活", "score": 5.6, "book_id": "6802547", "description": "《畅游日本》，本书的广大读者通过这本收，认识北海道、本州、四国、九州、冲绳等日本各地的多样魅力，亲身体验日本的人文与自然之美，为美好的明天注入新的活力，衰心..."},
{"name": "云南行知书", "url": "https://book.douban.com/subject/1317589/", "comment_num": 115, "sub_tag_name": "自助游", "tag_name": "生活", "score": 7.1, "book_id": "1317589", "description": "曾经，坐在泸沽湖畔，远处传来跳锅庄的人们的歌声笑语，面前是静谧幽暗的湖水，想象着一轮满月照在湖上，和三五知己把酒共话人世沧桑；曾经，纳西古乐散场后，独自走在..."},
{"name": "普吉岛", "url": "https://book.douban.com/subject/6749846/", "comment_num": 10, "sub_tag_name": "自助游", "tag_name": "生活", "score": 6.9, "book_id": "6749846", "description": "《梅里安旅行指南:普吉岛》内容简介：普吉岛是印度洋安达曼海上的一颗“明珠”，《梅里安旅行指南:普吉岛》向你呈现这个海岛的热带风情：纯净美丽的沙滩，倒映水中的..."},
{"name": "上海夜太High", "url": "https://book.douban.com/subject/1490293/", "comment_num": 34, "sub_tag_name": "自助游", "tag_name": "生活", "score": 7.7, "book_id": "1490293", "description": "戏剧性的故事、鲜为人知的夜游点，本书中上海私人夜生活地图，带你走近冷上海，走近上海的夜……上海，风情万种的大都市夜生活，带给人们不少美好的印象。本书中为你..."},
{"name": "开始在香港自助旅行", "url": "https://book.douban.com/subject/6011165/", "comment_num": 27, "sub_tag_name": "自助游", "tag_name": "生活", "score": 8.1, "book_id": "6011165", "description": "《开始在香港自助旅行》由土生土长的香港作者古弘基撰写，角度独特“情报”精准，同样的香港，他以招待朋友游览自己家乡般的热诚来介绍——到哪吃美食最“正港”、哪里..."},
{"name": "自行车骑行宝典", "url": "https://book.douban.com/subject/6905364/", "comment_num": 124, "sub_tag_name": "自助游", "tag_name": "生活", "score": 8.0, "book_id": "6905364", "description": "《自行车骑行宝典:单车学校教你的52堂课》讲述了如何骑车才能既健身又不损害身体？骑车怎么才能减肥？自行车装备怎么“备”？怎样骑车最省力？《自行车骑行宝典:单..."},
{"name": "ICan旅游系列", "url": "https://book.douban.com/subject/5336020/", "comment_num": 29, "sub_tag_name": "自助游", "tag_name": "生活", "score": 8.1, "book_id": "5336020", "description": "《ICan旅游系列:香港(全新版)》主要内容简介：最佳购物攻略，逐一搜寻香港人气商品最低采购点，详附大减价情报，全港名牌Outlet淘宝地图等专题，买尽国..."},
{"name": "北海道5天4夜", "url": "https://book.douban.com/subject/4240999/", "comment_num": 25, "sub_tag_name": "自助游", "tag_name": "生活", "score": 7.3, "book_id": "4240999", "description": "《地图随身:北海道5天4夜》内容简介：以7个北海道5天4夜以及开车畅游的建议玩法为始、44张详尽的地图和交通串联方式为主、景点和吃喝玩乐资讯为辅，强调亲切实..."},
{"name": "金色的辉煌,蓝色的梦境", "url": "https://book.douban.com/subject/4736435/", "comment_num": 10, "sub_tag_name": "自助游", "tag_name": "生活", "score": 0.0, "book_id": "4736435", "description": "《金色的辉煌,蓝色的梦境:希腊之旅》内容简介：“文明之路”迈锡尼：充满未解之谜，柏拉图“自由之地”——圣托里尼岛：慵懒自由的生活，黑色神秘：火山岛奇遇，仙女..."},
{"name": "杭州客", "url": "https://book.douban.com/subject/1429908/", "comment_num": 34, "sub_tag_name": "自助游", "tag_name": "生活", "score": 7.2, "book_id": "1429908", "description": "本书按照旅行者目的不同而分别提供了不同的行走路线，包括杭州美景路线、杭州美女秀衣/购物路线、杭州美居路线、美食路线、泡吧路线、健身路线及交通路线等。..."},
{"name": "香港澳门攻略完全制霸", "url": "https://book.douban.com/subject/4240920/", "comment_num": 39, "sub_tag_name": "自助游", "tag_name": "生活", "score": 7.5, "book_id": "4240920", "description": "《香港澳门攻略完全制霸》内容均为编辑部采访团队实地走访、考察而来，888个景点与店家的浩大采访工作量，只为能奉献给您更多、更新、更好的港澳旅游资讯。书中推荐..."},
{"name": "美国旅游", "url": "https://book.douban.com/subject/1488866/", "comment_num": 20, "sub_tag_name": "自助游", "tag_name": "生活", "score": 7.4, "book_id": "1488866", "description": "《美国旅游》地图部分包括总图、分州图、城市图、景点图以及历史图。其中总图4幅，含地形、政区、旅游和高速公路；分州图46幅；城市图46幅；景点图21幅；历史图..."},
{"name": "完全自游意大利", "url": "https://book.douban.com/subject/5405143/", "comment_num": 18, "sub_tag_name": "自助游", "tag_name": "生活", "score": 7.7, "book_id": "5405143", "description": "完全自游意大利，ISBN：9787030295385，作者：墨刻编辑部编著"},
{"name": "新疆/藏羚羊自助旅行手册", "url": "https://book.douban.com/subject/1094034/", "comment_num": 12, "sub_tag_name": "自助游", "tag_name": "生活", "score": 7.7, "book_id": "1094034", "description": "对所有的年青人而言，拓展生命空间，增长见识，学习对不同地域、不同民族、不同生存状态和价值观的关爱和欣赏都是我们成长过程中的真义所在。因此旅行就成为必然。..."},
{"name": "四川重庆行知书", "url": "https://book.douban.com/subject/1136602/", "comment_num": 48, "sub_tag_name": "自助游", "tag_name": "生活", "score": 7.6, "book_id": "1136602", "description": "行走，继续行走。至贡嘎山，至甘孜州；至秋天深处的黄龙九寨沟；还有丹巴的美人谷和康巴汉子……无畏艰辛和险阻，追求和发现自己心目中的香巴拉。本书全面深刻介绍了四..."},
{"name": "完全自游土耳其", "url": "https://book.douban.com/subject/5405142/", "comment_num": 15, "sub_tag_name": "自助游", "tag_name": "生活", "score": 7.7, "book_id": "5405142", "description": "《完全自游土耳其》内容涵盖的区域除了必访的土耳其金三角：伊斯坦布尔、卡帕多西亚和棉花堡之外，还扩及到地中海、爱琴海、安纳托利亚等地区，以及比较冷门的土耳其东..."},
{"name": "Myanmar", "url": "https://book.douban.com/subject/1791797/", "comment_num": 15, "sub_tag_name": "自助游", "tag_name": "生活", "score": 8.4, "book_id": "1791797", "description": "Explorethevast,ancientruinsofBagan,voyageupmyriadwaterwaysbyriver..."},
{"name": "大美山西", "url": "https://book.douban.com/subject/3212688/", "comment_num": 20, "sub_tag_name": "自助游", "tag_name": "生活", "score": 7.0, "book_id": "3212688", "description": "本书将为您提供包括交通、预算、住宿、美食、景点等众多方面的信息，为您的出游提供全面的建议：有“往返交通“、“区内交通”、“相连景点交通”等交通信息；有经济档..."},
{"name": "开始在美国自助旅行", "url": "https://book.douban.com/subject/2678354/", "comment_num": 73, "sub_tag_name": "自助游", "tag_name": "生活", "score": 7.5, "book_id": "2678354", "description": "开始在美国自助旅行，ISBN：9787563716173，作者：陈婉娜"},
{"name": "好客山东导游词", "url": "https://book.douban.com/subject/3463625/", "comment_num": 10, "sub_tag_name": "自助游", "tag_name": "生活", "score": 0.0, "book_id": "3463625", "description": "《好客山东导游词》主要内容：各位朋友，早在2500多年前，“至圣先师”孔子就发出了“有朋自远方来，不亦乐乎！”的真挚邀请。今天，热情好客的9367万山东人民..."},
{"name": "英国玩全攻略", "url": "https://book.douban.com/subject/5936591/", "comment_num": 16, "sub_tag_name": "自助游", "tag_name": "生活", "score": 7.3, "book_id": "5936591", "description": "《英国玩全攻略(2013-2014全彩版)》涵盖白金汉宫、国会大厦、大本钟、大英博物馆、伦敦塔、伦敦眼、泰晤士河、查令十字街、海德公园、温布利球场、爱丁堡城..."},
{"name": "四川（走遍中国）", "url": "https://book.douban.com/subject/1897738/", "comment_num": 39, "sub_tag_name": "自助游", "tag_name": "生活", "score": 7.5, "book_id": "1897738", "description": "《四川》(走遍中国)是《走遍中国》系列中的一本，该系列作为一套以实用信息为主的自助旅行丛书，其尽可能地向读者提供最全面的信息，包括出发前需要了解的相关的人文..."},
{"name": "台湾自助游", "url": "https://book.douban.com/subject/25775625/", "comment_num": 15, "sub_tag_name": "自助游", "tag_name": "生活", "score": 7.8, "book_id": "25775625", "description": "米其林向中国市场推出第十五本中文版旅游指南(又名“绿色指南”)——《台湾自助游》，这也是米其林指南继《普罗旺斯自助游》之后的第二本地区域性旅游指南，与此同时..."},
{"name": "带一本书去广州", "url": "https://book.douban.com/subject/1400033/", "comment_num": 48, "sub_tag_name": "自助游", "tag_name": "生活", "score": 7.1, "book_id": "1400033", "description": "带一本书去广州，ISBN：9787502345464，作者：肖楠编著、摄影；李潇宇插图"},
{"name": "瑞士", "url": "https://book.douban.com/subject/1648403/", "comment_num": 29, "sub_tag_name": "自助游", "tag_name": "生活", "score": 6.6, "book_id": "1648403", "description": "《瑞士》(藏羚羊自助游)主要面对那些喜爱到欧洲尤其是瑞士旅游的自助游读者，对于一个中国游客，尤其是自助旅行者，瑞士最大的吸引力是什么呢？　　首先瑞士是一个..."},
{"name": "搭地铁游东京（第2版）", "url": "https://book.douban.com/subject/25897410/", "comment_num": 14, "sub_tag_name": "自助游", "tag_name": "生活", "score": 7.3, "book_id": "25897410", "description": "蚂蜂窝旅游达人绝密推荐搭地铁玩转首尔省时省钱省时省钱搭地铁，吃喝玩乐ALLINMAP精选蚂蜂窝人气攻略，让真正的旅行达人教你如何搭地铁游首尔超实..."},
{"name": "2008去北京", "url": "https://book.douban.com/subject/2978142/", "comment_num": 13, "sub_tag_name": "自助游", "tag_name": "生活", "score": 7.6, "book_id": "2978142", "description": "八位资深背包客历时一年，遍访七个2008年奥运会承办城市的奥运场馆、胡同、皇城、寺庙、老街、以优美、流畅的文笔诠释奥运人文景观，倾情推荐最佳交通、美食、住宿..."},
{"name": "甘肃宁夏行知书", "url": "https://book.douban.com/subject/1127588/", "comment_num": 38, "sub_tag_name": "自助游", "tag_name": "生活", "score": 7.0, "book_id": "1127588", "description": "西走河西，南下甘南，然后宁夏……　　有艰辛，有温情，有沉默，有惊诧还有理想和行走的一切意味。因为甘宁就在那里，因为我们在行走。　　行走甘宁的N个理由..."},
{"name": "穿火车", "url": "https://book.douban.com/subject/10801511/", "comment_num": 17, "sub_tag_name": "自助游", "tag_name": "生活", "score": 6.9, "book_id": "10801511", "description": "《穿火车:\"三个80后傻瓜\"14000公里摩行记》终于与大家见面啦！这是我们三人约定要完成的事。《穿火车:\"三个80后傻瓜\"14000公里摩行记》分为五章，..."},
{"name": "最美中原", "url": "https://book.douban.com/subject/6960422/", "comment_num": 10, "sub_tag_name": "自助游", "tag_name": "生活", "score": 7.4, "book_id": "6960422", "description": "《最美中原:从洛阳到商丘》：现代社会越来越追求有个性有特色的旅行，淡化走马观花的传统方式，追求历史文化民俗的深度感悟、风景美食住宿的独特体验。《最美旅游线..."},
{"name": "滇西北-走出来的旅行指南", "url": "https://book.douban.com/subject/2115935/", "comment_num": 10, "sub_tag_name": "自助游", "tag_name": "生活", "score": 7.9, "book_id": "2115935", "description": "这本旅游指南旨在有重点推荐滇西北风情旅游，注重路线的连贯，为旅行者提供最详细、最全面、最深入、最新的旅游资讯。书中详细介绍多数旅行者向往的旅游者热点地区，还..."},
{"name": "搭地铁玩香港", "url": "https://book.douban.com/subject/2568658/", "comment_num": 44, "sub_tag_name": "自助游", "tag_name": "生活", "score": 7.5, "book_id": "2568658", "description": "《搭地铁玩香港(最新版)》内容简介：地铁作为城市的地下脉络，已成为城市越来越不可分割的部分，由于其覆盖范围广，设置站点的密度大，加上行车速度快，往返班次多，..."},
{"name": "云南自助游2012-2013版", "url": "https://book.douban.com/subject/10774607/", "comment_num": 10, "sub_tag_name": "自助游", "tag_name": "生活", "score": 6.7, "book_id": "10774607", "description": "《云南自助游(2012-2013版)》详细介绍了云南的旅游景点，并为读者提供了云南的历史、地理、宗教、气候、民俗等方面的背景资料，与上一版相比增加了特色云南..."},
{"name": "芝麻开门伊斯坦布尔", "url": "https://book.douban.com/subject/10060161/", "comment_num": 30, "sub_tag_name": "自助游", "tag_name": "生活", "score": 6.8, "book_id": "10060161", "description": "在世界上唯一横跨欧亚两洲的城市里，一会儿在欧洲区与老城摩挲,到老街晃游,一会儿又搭上渡轮前往亚洲。旅人期待从接触到的两地人事物中,抽剥出丰饶趣味。每天都有这..."},
{"name": "千元自助游", "url": "https://book.douban.com/subject/1082910/", "comment_num": 20, "sub_tag_name": "自助游", "tag_name": "生活", "score": 7.1, "book_id": "1082910", "description": "随着我国人民生活水平的不断提高，外出旅游已成为多数人的流行时尚。对于一个旅游者来说，一本详尽实用的旅游手册不可或缺。《千元自助游》邀请资深旅游专家撰写，资料..."},
{"name": "千元游中国", "url": "https://book.douban.com/subject/2114184/", "comment_num": 15, "sub_tag_name": "自助游", "tag_name": "生活", "score": 7.2, "book_id": "2114184", "description": "本书精选国内时下人气最旺的18条线路，纵横大江南北，兼具各地风土人情，全部由自助旅行家亲自采线、编写，并且延续了《藏羚羊自动游》一贯的实用原则，在七天内的日..."},
{"name": "完全自游英国", "url": "https://book.douban.com/subject/5405145/", "comment_num": 10, "sub_tag_name": "自助游", "tag_name": "生活", "score": 0.0, "book_id": "5405145", "description": "《完全自游英国(2012-2013升级版)》是由墨刻编辑部编著，将从“英国十大必体验”、“超完美行程规划”、“食尚英国”等主题开端，让读者快速建议英国印象，..."},
{"name": "触摸天堂的骑士", "url": "https://book.douban.com/subject/4058634/", "comment_num": 48, "sub_tag_name": "自助游", "tag_name": "生活", "score": 6.2, "book_id": "4058634", "description": "《触摸天堂的骑士:骑行滇藏》内容简介：骑自行车走滇藏线这个愿望，由来已久。自从上次匆匆告别西藏，就总在梦里一次次地回去。那片土地令我魂牵梦萦。有清幽山谷中寂..."},
{"name": "150美金玩转东南亚越南", "url": "https://book.douban.com/subject/6040879/", "comment_num": 21, "sub_tag_name": "自助游", "tag_name": "生活", "score": 5.7, "book_id": "6040879", "description": "《150美金玩转东南亚越南》主要内容：越南的女人普遍很能干，街道摆小摊的游商或是商场内的服务员，大部分都是女性。她们仿佛身经百战，力大如牛，我常常看到她们挑..."},
{"name": "150美金玩转东南亚柬埔寨", "url": "https://book.douban.com/subject/6040878/", "comment_num": 14, "sub_tag_name": "自助游", "tag_name": "生活", "score": 5.4, "book_id": "6040878", "description": "《150美金玩转东南亚柬埔寨》主要内容：就在太阳即将跃出地平线时，云层又突然变厚。每一天，同样的场景都在上演，如果能持之以恒，肯定会看到那个美丽时刻。只不过..."},
{"name": "香港+九龍、新界及離島香港食玩買終極天書11-12完全版", "url": "https://book.douban.com/subject/10525002/", "comment_num": 10, "sub_tag_name": "自助游", "tag_name": "生活", "score": 0.0, "book_id": "10525002", "description": "集齊香港、九龍、新界及離島，包括：中環、尖沙咀、旺角、佐敦、西貢及南丫島等共18個區，必遊熱點超過400個。收入香港7大必遊經典、最強手信巡禮、血拼OU..."},
{"name": "名镇天下", "url": "https://book.douban.com/subject/1392737/", "comment_num": 10, "sub_tag_name": "自助游", "tag_name": "生活", "score": 7.9, "book_id": "1392737", "description": "广东数量众多的古镇古村，经过千百年数百代人的繁衍，形成了各式各样的人文，包括风土人情，包括民俗文化，包括世代相传的精神。在鹤舞与碉楼、牌坊与宗祠、辈分与村规..."},
{"name": "2012-2013-完全自游南法普罗旺斯蔚蓝海岸-升级版", "url": "https://book.douban.com/subject/5405146/", "comment_num": 11, "sub_tag_name": "自助游", "tag_name": "生活", "score": 7.6, "book_id": "5405146", "description": "《完全自游南法•普罗旺斯•蔚蓝海岸(全彩)》内容简介：特别规划经典艺术之旅、普罗旺斯薰衣草地图、直播五大节庆、蔚蓝海岸大比拼，让你的南法之行更丰富、更有趣、..."},
{"name": "西藏-走出来的旅行指南", "url": "https://book.douban.com/subject/2115216/", "comment_num": 10, "sub_tag_name": "自助游", "tag_name": "生活", "score": 0.0, "book_id": "2115216", "description": "交通，这是本书的最大特色所在，我们为读者提供了“往返交通”、“区内交通”、“相连景点交通”等信息，核心是“以住宿点为中心的区内交通”。在本书中，大到城市之..."},
{"name": "搭地铁游巴黎（第2版）", "url": "https://book.douban.com/subject/25897412/", "comment_num": 10, "sub_tag_name": "自助游", "tag_name": "生活", "score": 0.0, "book_id": "25897412", "description": "蚂蜂窝旅游达人绝密推荐搭地铁玩转巴黎省时省钱省时省钱搭地铁，吃喝玩乐ALLINMAP精选蚂蜂窝人气攻略，让真正的旅行达人教你如何搭地铁游巴黎超实..."},
{"name": "川滇线快乐自助游", "url": "https://book.douban.com/subject/1988783/", "comment_num": 22, "sub_tag_name": "自助游", "tag_name": "生活", "score": 6.4, "book_id": "1988783", "description": "来自四川滇线上：古镇、雪山、湖泊、小城、村、寨、峡谷、公园、森林、牧场、寺庙、酒吧、茶楼、商铺、要塞、水畔、青年旅舍……n个侧面，27个民族，39个国家，五..."},
{"name": "走遍中国", "url": "https://book.douban.com/subject/2382017/", "comment_num": 26, "sub_tag_name": "自助游", "tag_name": "生活", "score": 6.9, "book_id": "2382017", "description": "《走遍中国:福建》尽可能地向读者提供最全面的信息，包括出发前需要了解的福建相关的人文地理知识，准备出发时所应掌握的衣、食、住、行的资讯以及大量来自福建的景点..."},
{"name": "最南京", "url": "https://book.douban.com/subject/5413274/", "comment_num": 16, "sub_tag_name": "自助游", "tag_name": "生活", "score": 6.6, "book_id": "5413274", "description": "《最南京》从历史、文化、景观、购物、美食等方面细数南京的经典之地，向读者展现了一个最不可错过的南京。散落全篇的“游玩攻略”尽显从读者角度的贴心考虑。《最南京..."},
{"name": "迷失东非", "url": "https://book.douban.com/subject/22279315/", "comment_num": 10, "sub_tag_name": "自助游", "tag_name": "生活", "score": 7.3, "book_id": "22279315", "description": null},
{"name": "易行1丽江攻略", "url": "https://book.douban.com/subject/1841979/", "comment_num": 10, "sub_tag_name": "自助游", "tag_name": "生活", "score": 0.0, "book_id": "1841979", "description": "易行丽江攻略，ISBN：9787503228933，作者：陈霖主编"},
{"name": "旅行小贴士", "url": "https://book.douban.com/subject/1920636/", "comment_num": 242, "sub_tag_name": "自助游", "tag_name": "生活", "score": 7.4, "book_id": "1920636", "description": "通过这本小册子，LonelyPlanet公司和生活·读书·新知三联书店试图帮助旅行者们迈出认识和发现这个辽阔广大、精彩美丽的世界的第一步，让你了解到在出发..."},
{"name": "中国自助游第十四版", "url": "https://book.douban.com/subject/25747358/", "comment_num": 10, "sub_tag_name": "自助游", "tag_name": "生活", "score": 0.0, "book_id": "25747358", "description": "13年了，你很难看到一本旅游攻略能像它如此功能齐全，实用风趣。在寻找启程目的地时，它内容详尽得简直就是个绝佳的出行指南针；在旅途中失去头绪时，它又成了一位指..."},
{"name": "户外养育新理念", "url": "https://book.douban.com/subject/3743359/", "comment_num": 10, "sub_tag_name": "自助游", "tag_name": "生活", "score": 0.0, "book_id": "3743359", "description": "《户外养育新理念》当我们面对孩子时，是否偶尔会想起自己的童年，孤独地坐在村口的小溪边，面对落日夕阳，想像着外面的世界……我们是否还记得，童年时曾经流着口水在..."},
{"name": "自助玩转六大洲", "url": "https://book.douban.com/subject/6535452/", "comment_num": 14, "sub_tag_name": "自助游", "tag_name": "生活", "score": 6.7, "book_id": "6535452", "description": "《自助玩转六大洲》内容主要包括：柬埔寨旅游、签证事件、快饿死了、金边——吴哥、敷衍的服务员、初入吴哥、再入吴哥、越南小姑娘、我要上学、有条瀑布、被骗了、又是..."},
{"name": "大勇和小花的欧洲日记Ⅱ", "url": "https://book.douban.com/subject/2299194/", "comment_num": 567, "sub_tag_name": "自助游", "tag_name": "生活", "score": 8.2, "book_id": "2299194", "description": "带着对茜茜公主故乡的美好想象，踏上16日德、奥自助行程，不必匆匆忙忙地赶路，借助从不晚点的德国交通系统和准备充分的线路攻略，度过又一个悠闲的欧洲假日：在莱茵..."},
{"name": "华南自助游", "url": "https://book.douban.com/subject/1492983/", "comment_num": 10, "sub_tag_name": "自助游", "tag_name": "生活", "score": 0.0, "book_id": "1492983", "description": "本书通过科学合理、周密详细的编辑，以精彩恰当的文辞对当今华南旅游现状做出一番详细解说，更能加深人们对华北的自然风光及人文景观的迷恋与向往。1.景区..."},
{"name": "独行侠65天走遍申根25国", "url": "https://book.douban.com/subject/6311394/", "comment_num": 98, "sub_tag_name": "自助游", "tag_name": "生活", "score": 7.2, "book_id": "6311394", "description": "《独行侠65天走遍申根25国》的作者黄喆，是一位拥有丰富旅行经验的资深“老驴”，也是一位以独行独游为乐、深谙生活之趣的“独行侠”。2008年欧洲申根签证扩大..."},
{"name": "贵州", "url": "https://book.douban.com/subject/6425967/", "comment_num": 230, "sub_tag_name": "自助游", "tag_name": "生活", "score": 8.2, "book_id": "6425967", "description": "《LonelyPlanet中国旅行指南系列:贵州》主要内容简介：苍翠幽深的原始森林，紫红色沉着艳丽的泥石，万千风姿的瀑布群，竭尽人类所有幻想的溶洞——这就..."},
{"name": "北疆", "url": "https://book.douban.com/subject/2182005/", "comment_num": 10, "sub_tag_name": "自助游", "tag_name": "生活", "score": 0.0, "book_id": "2182005", "description": "北疆：走出来的旅行指南，ISBN：9787110065174，作者：赵宗锋"},
{"name": "Insight旅行指南：美国", "url": "https://book.douban.com/subject/25872241/", "comment_num": 10, "sub_tag_name": "自助游", "tag_name": "生活", "score": 0.0, "book_id": "25872241", "description": null},
{"name": "江苏上海古镇书", "url": "https://book.douban.com/subject/1217511/", "comment_num": 23, "sub_tag_name": "自助游", "tag_name": "生活", "score": 6.8, "book_id": "1217511", "description": "全面精选二十五座古镇，代表了江苏、上海境内古镇的不同风格，堪称经典；真实所收录的古镇全部经过紫图《古镇书编辑部》特派记者亲历实地的采访和拍摄，来自当地的第一..."},
{"name": "LonelyPlanet孤独星球:东北（2014年版）", "url": "https://book.douban.com/subject/26247176/", "comment_num": 69, "sub_tag_name": "自助游", "tag_name": "生活", "score": 7.5, "book_id": "26247176", "description": "从北极村到旅顺口，从零下30℃到零上30℃，这片历经沧桑的黑土地在一次次冰雪消融后重焕生机。这里有冰天雪地里的热情奔放，可以满足你对冰雪与寒冷的所有想象；有..."},
{"name": "OnceWhileTravelling", "url": "https://book.douban.com/subject/1885160/", "comment_num": 22, "sub_tag_name": "自助游", "tag_name": "生活", "score": 8.3, "book_id": "1885160", "description": "FoundersofthephenomenallysuccessfulpublishingcompanyLonelyPlanet,Tony..."},
{"name": "人生必去的101个地方", "url": "https://book.douban.com/subject/10466005/", "comment_num": 10, "sub_tag_name": "自助游", "tag_name": "生活", "score": 7.7, "book_id": "10466005", "description": "《世界印象•人生必去的101个地方(外国篇)》内容简介：综合多家专业旅游网站的景点排名，介绍最受欢迎的旅游热点。每一篇文章和每一幅图片，都能带给读者身临其境..."},
{"name": "杭州客", "url": "https://book.douban.com/subject/1429908/", "comment_num": 34, "sub_tag_name": "自助游", "tag_name": "生活", "score": 7.2, "book_id": "1429908", "description": "本书按照旅行者目的不同而分别提供了不同的行走路线，包括杭州美景路线、杭州美女秀衣/购物路线、杭州美居路线、美食路线、泡吧路线、健身路线及交通路线等。..."},
{"name": "最南京", "url": "https://book.douban.com/subject/5413274/", "comment_num": 16, "sub_tag_name": "自助游", "tag_name": "生活", "score": 6.6, "book_id": "5413274", "description": "《最南京》从历史、文化、景观、购物、美食等方面细数南京的经典之地，向读者展现了一个最不可错过的南京。散落全篇的“游玩攻略”尽显从读者角度的贴心考虑。《最南京..."},
{"name": "东南亚", "url": "https://book.douban.com/subject/1963229/", "comment_num": 1160, "sub_tag_name": "自助游", "tag_name": "生活", "score": 8.6, "book_id": "1963229", "description": "这本被誉为“黄色圣经”的旅行指南，是LonelyPlanet最早和最精彩的一本书，也是你前往东南亚，经历无穷无尽激动人心的奇遇的叩门砖。想体验永不停息的2..."},
{"name": "2012-2013-完全自游南法普罗旺斯蔚蓝海岸-升级版", "url": "https://book.douban.com/subject/5405146/", "comment_num": 11, "sub_tag_name": "自助游", "tag_name": "生活", "score": 7.6, "book_id": "5405146", "description": "《完全自游南法•普罗旺斯•蔚蓝海岸(全彩)》内容简介：特别规划经典艺术之旅、普罗旺斯薰衣草地图、直播五大节庆、蔚蓝海岸大比拼，让你的南法之行更丰富、更有趣、..."},
{"name": "完全自游英国", "url": "https://book.douban.com/subject/5405145/", "comment_num": 10, "sub_tag_name": "自助游", "tag_name": "生活", "score": 0.0, "book_id": "5405145", "description": "《完全自游英国(2012-2013升级版)》是由墨刻编辑部编著，将从“英国十大必体验”、“超完美行程规划”、“食尚英国”等主题开端，让读者快速建议英国印象，..."},
{"name": "京都，中途下车", "url": "https://book.douban.com/subject/20458703/", "comment_num": 53, "sub_tag_name": "自助游", "tag_name": "生活", "score": 7.1, "book_id": "20458703", "description": "距离、陌生、未知、再加上几分冒险，挑动着爱做梦的旅人的心，陌生人的善意和亲切，萍水相遇时的相互体贴，为旅行带来更多不可预期的快乐。在京都这座融合了传统与现代..."},
{"name": "完全自游土耳其", "url": "https://book.douban.com/subject/5405142/", "comment_num": 15, "sub_tag_name": "自助游", "tag_name": "生活", "score": 7.7, "book_id": "5405142", "description": "《完全自游土耳其》内容涵盖的区域除了必访的土耳其金三角：伊斯坦布尔、卡帕多西亚和棉花堡之外，还扩及到地中海、爱琴海、安纳托利亚等地区，以及比较冷门的土耳其东..."},
{"name": "ICan旅游系列", "url": "https://book.douban.com/subject/5336020/", "comment_num": 29, "sub_tag_name": "自助游", "tag_name": "生活", "score": 8.1, "book_id": "5336020", "description": "《ICan旅游系列:香港(全新版)》主要内容简介：最佳购物攻略，逐一搜寻香港人气商品最低采购点，详附大减价情报，全港名牌Outlet淘宝地图等专题，买尽国..."},
{"name": "高原上", "url": "https://book.douban.com/subject/27001284/", "comment_num": 16, "sub_tag_name": "自助游", "tag_name": "生活", "score": 9.6, "book_id": "27001284", "description": "《高原上》一书是两位作者一家三人由澳大利亚出发，在南美洲旅行的游记，记录了他们在圣地亚哥、布宜诺斯艾利斯、利马等城市和秘鲁高原上旅行的所见所想，在这些游记中..."},
{"name": "老爸老妈去旅行", "url": "https://book.douban.com/subject/1940182/", "comment_num": 549, "sub_tag_name": "自助游", "tag_name": "生活", "score": 7.6, "book_id": "1940182", "description": "这本书绝不仅仅是游记，更是关于生活态度和方式的记录。一对上海退休夫妻老杨老张，非官非商，不懂外语，也不熟悉网络，不参加旅游团也没人全陪，凭着喜爱和勇气，淡..."},
{"name": "LonelyPlanet:巴黎(2015年全新版)", "url": "https://book.douban.com/subject/26585219/", "comment_num": 25, "sub_tag_name": "自助游", "tag_name": "生活", "score": 8.1, "book_id": "26585219", "description": "对于每个到访者来说，巴黎标志性的建筑、精致的美食、时髦的精品店和无价的艺术珍品，都具有一种超越时空的亲切感——初次见面却毫不陌生的埃菲尔铁塔的铁制尖顶、雄伟..."},
{"name": "背包客", "url": "https://book.douban.com/subject/4915970/", "comment_num": 296, "sub_tag_name": "自助游", "tag_name": "生活", "score": 7.6, "book_id": "4915970", "description": "《背包客》是一本背包客必备指导手册，它从背包出游的筹划与准备工作开始谈起，介绍了如何在出发前锻炼出强健的体魄，如何增强长途旅行的耐力和灵敏度，并提供了背包客..."},
{"name": "150美金玩转东南亚柬埔寨", "url": "https://book.douban.com/subject/6040878/", "comment_num": 14, "sub_tag_name": "自助游", "tag_name": "生活", "score": 5.4, "book_id": "6040878", "description": "《150美金玩转东南亚柬埔寨》主要内容：就在太阳即将跃出地平线时，云层又突然变厚。每一天，同样的场景都在上演，如果能持之以恒，肯定会看到那个美丽时刻。只不过..."},
{"name": "香港澳门攻略完全制霸", "url": "https://book.douban.com/subject/4240920/", "comment_num": 39, "sub_tag_name": "自助游", "tag_name": "生活", "score": 7.5, "book_id": "4240920", "description": "《香港澳门攻略完全制霸》内容均为编辑部采访团队实地走访、考察而来，888个景点与店家的浩大采访工作量，只为能奉献给您更多、更新、更好的港澳旅游资讯。书中推荐..."},
{"name": "出发.才能到达-3000美金周游世界", "url": "https://book.douban.com/subject/10732778/", "comment_num": 284, "sub_tag_name": "自助游", "tag_name": "生活", "score": 6.0, "book_id": "10732778", "description": "3000美金，全球28个国家和地区，不打工，不吃面包咸菜，飞机出行，五星级酒店入住。我最便宜的机票不到八分钱，一听可口可乐在英国街上的售价是1英镑，一根黄..."},
{"name": "柬埔寨", "url": "https://book.douban.com/subject/1968295/", "comment_num": 770, "sub_tag_name": "自助游", "tag_name": "生活", "score": 8.3, "book_id": "1968295", "description": "使用LonelyPlanet旅行指南的最让人开心的，就是你可以选择任何自己喜欢的旅行方式。LonelyPlanet相信，旅行中最难忘的经历往往是那此出乎..."},
{"name": "泰国", "url": "https://book.douban.com/subject/3204670/", "comment_num": 338, "sub_tag_name": "自助游", "tag_name": "生活", "score": 8.3, "book_id": "3204670", "description": "搜寻泰国最好的街边小摊。享受绝妙的美食。跳上长尾船或小岛，走进属于你一人的海滩天堂。在泼水节上浑身湿透。这是泰国传统的新年，是世界上最为壮观的泼水战场。..."},
{"name": "开始在美国自助旅行", "url": "https://book.douban.com/subject/2678354/", "comment_num": 73, "sub_tag_name": "自助游", "tag_name": "生活", "score": 7.5, "book_id": "2678354", "description": "开始在美国自助旅行，ISBN：9787563716173，作者：陈婉娜"},
{"name": "贵州", "url": "https://book.douban.com/subject/6425967/", "comment_num": 230, "sub_tag_name": "自助游", "tag_name": "生活", "score": 8.2, "book_id": "6425967", "description": "《LonelyPlanet中国旅行指南系列:贵州》主要内容简介：苍翠幽深的原始森林，紫红色沉着艳丽的泥石，万千风姿的瀑布群，竭尽人类所有幻想的溶洞——这就..."},
{"name": "中国最美的88个特色旅游地", "url": "https://book.douban.com/subject/6101663/", "comment_num": 28, "sub_tag_name": "自助游", "tag_name": "生活", "score": 7.6, "book_id": "6101663", "description": "“最美中国系列”丛书是旅游圣经团队历经数年发展、走遍中国后推出的巅峰之作。团队组织所有优秀作者撰写本系列，可谓十余位资深背包客视野中的“最美中国”。本系列丛..."},
{"name": "徒步旅行耶路撒冷", "url": "https://book.douban.com/subject/27116677/", "comment_num": 14, "sub_tag_name": "自助游", "tag_name": "生活", "score": 7.7, "book_id": "27116677", "description": "本书共分为十二章，第一章是简明的“生存指南”，集中介绍耶路撒冷的气温、酒店、餐饮情况。第二到十二章是对景点的细节描述。作者不仅介绍了大多数游人非去不可的哭墙..."},
{"name": "乌镇的似水年华", "url": "https://book.douban.com/subject/1154227/", "comment_num": 58, "sub_tag_name": "自助游", "tag_name": "生活", "score": 7.4, "book_id": "1154227", "description": "乌镇，在我们的心目中，是一个诗意的梦境之地，需要一颗颗温柔的心意来观照，来感悟。所以，这本书没有地图，没有旅游指南，没有景点描述，也没有背景交代，甚至每一..."},
{"name": "户外养育新理念", "url": "https://book.douban.com/subject/3743359/", "comment_num": 10, "sub_tag_name": "自助游", "tag_name": "生活", "score": 0.0, "book_id": "3743359", "description": "《户外养育新理念》当我们面对孩子时，是否偶尔会想起自己的童年，孤独地坐在村口的小溪边，面对落日夕阳，想像着外面的世界……我们是否还记得，童年时曾经流着口水在..."},
{"name": "Myanmar", "url": "https://book.douban.com/subject/1791797/", "comment_num": 15, "sub_tag_name": "自助游", "tag_name": "生活", "score": 8.4, "book_id": "1791797", "description": "Explorethevast,ancientruinsofBagan,voyageupmyriadwaterwaysbyriver..."},
{"name": "美国旅游", "url": "https://book.douban.com/subject/1488866/", "comment_num": 20, "sub_tag_name": "自助游", "tag_name": "生活", "score": 7.4, "book_id": "1488866", "description": "《美国旅游》地图部分包括总图、分州图、城市图、景点图以及历史图。其中总图4幅，含地形、政区、旅游和高速公路；分州图46幅；城市图46幅；景点图21幅；历史图..."},
{"name": "北疆", "url": "https://book.douban.com/subject/2182005/", "comment_num": 10, "sub_tag_name": "自助游", "tag_name": "生活", "score": 0.0, "book_id": "2182005", "description": "北疆：走出来的旅行指南，ISBN：9787110065174，作者：赵宗锋"},
{"name": "易行1丽江攻略", "url": "https://book.douban.com/subject/1841979/", "comment_num": 10, "sub_tag_name": "自助游", "tag_name": "生活", "score": 0.0, "book_id": "1841979", "description": "易行丽江攻略，ISBN：9787503228933，作者：陈霖主编"},
{"name": "推着妈妈去旅行", "url": "https://book.douban.com/subject/25866807/", "comment_num": 17, "sub_tag_name": "自助游", "tag_name": "生活", "score": 8.0, "book_id": "25866807", "description": "80后北京青年樊蒙，推着坐轮椅的妈妈，从北京出发徒步到达西双版纳的旅行经历。这段历时数月，总行程3300公里，徒步穿越六个省的母子行，可谓“步步惊心”，但也..."},
{"name": "触摸天堂的骑士", "url": "https://book.douban.com/subject/4058634/", "comment_num": 48, "sub_tag_name": "自助游", "tag_name": "生活", "score": 6.2, "book_id": "4058634", "description": "《触摸天堂的骑士:骑行滇藏》内容简介：骑自行车走滇藏线这个愿望，由来已久。自从上次匆匆告别西藏，就总在梦里一次次地回去。那片土地令我魂牵梦萦。有清幽山谷中寂..."},
{"name": "伊本·白图泰游记", "url": "https://book.douban.com/subject/26545166/", "comment_num": 13, "sub_tag_name": "自助游", "tag_name": "生活", "score": 7.2, "book_id": "26545166", "description": "伊本·白图泰于弱冠之年离乡远游伊斯兰各国。1333年至印度德里，留居9年；1345年游历广州、杭州等地，1347年至印度，1349年返回摩洛哥，后又去西班牙..."},
{"name": "走吧醉宁波", "url": "https://book.douban.com/subject/1170394/", "comment_num": 10, "sub_tag_name": "自助游", "tag_name": "生活", "score": 0.0, "book_id": "1170394", "description": "吾乡宁波是浙东的文化之乡，因之也是江南旅游的胜地。而宁波人的认真、执着与开拓精神应该就是它今日繁华的来由吧！本书不是一般性的景点介绍，而是将这块历..."},
{"name": "中国四季游指南", "url": "https://book.douban.com/subject/2975579/", "comment_num": 10, "sub_tag_name": "自助游", "tag_name": "生活", "score": 0.0, "book_id": "2975579", "description": "《中国四季游指南》是一本以季节性为指导的旅游图书，它以四季为纲，月份为目，紧紧围绕景点的最佳游季进行介绍。特别是对于那些季节性强的景点还具体到了“日”，这样..."},
{"name": "LonelyPlanetAfrica", "url": "https://book.douban.com/subject/2940695/", "comment_num": 10, "sub_tag_name": "自助游", "tag_name": "生活", "score": 0.0, "book_id": "2940695", "description": "在线阅读本书DiscoverAfricaWatchthesunsetovertheNigeratMopti,where..."},
{"name": "地铁达人逛北京", "url": "https://book.douban.com/subject/5981318/", "comment_num": 10, "sub_tag_name": "自助游", "tag_name": "生活", "score": 0.0, "book_id": "5981318", "description": "《地铁达人逛北京》囊括北京已通车的13条地铁线路，配以75幅地铁站周边详图及11幅特色景区扩大图，含440个热门景点。《地铁达人逛北京》最大的特点是地铁站点..."},
{"name": "11元的铁道旅行", "url": "https://book.douban.com/subject/5986543/", "comment_num": 1085, "sub_tag_name": "自助游", "tag_name": "生活", "score": 7.5, "book_id": "5986543", "description": "何谓“11元铁路旅行”？台湾最慢的火车，最短区间的里程，最便宜的旅次，票价是11元。简言之，11元潜藏着，缓慢的节奏、淳朴的生活、迷人的风物。作者从台湾..."},
{"name": "桂林旅游圣经", "url": "https://book.douban.com/subject/2974570/", "comment_num": 10, "sub_tag_name": "自助游", "tag_name": "生活", "score": 0.0, "book_id": "2974570", "description": "最全面、最深入的大桂林地区旅行秘籍，中国山水的嘉年华，小资的圣地，背包客的天堂。这里不仅有桂林城、漓江、阳朔，还有龙脊梯田、资江、录渠、猫儿山……最详尽..."}]